Workbook

Sheet Summary
A1: DuPage County 2025 Tax Sale – Revised Bid Totals
A2: Removed: certs under $3,000 where both installments are delinquent (HalfInstallment = FALSE). Commercial = ClassCode "60 - Commercial Improvements".
A4: Category | B4: Cert Count | C4: Dollar Amount
A5: Revised Non-Commercial (Residential) | B5: =COUNTA('Revised Non-Commercial'!L2:L10000) -> 1142 | C5: =SUMIFS('Revised Non-Commercial'!AC2:AC10000,'Revised Non-Commercial'!L2:L10000,"<>") -> 8273859.2
A6: Commercial | B6: =COUNTA(Commercial!L2:L10000) -> 23 | C6: =SUMIFS(Commercial!AC2:AC10000,Commercial!L2:L10000,"<>") -> 1053093.8
A7: Revised Total (keep) | B7: =B5+B6 -> 1165 | C7: =C5+C6 -> 9326953
A9: Removed – Full Inst Under $3,000 | B9: =COUNTA('Removed - Full Inst Under 3K'!L2:L10000) -> 73 | C9: =SUMIFS('Removed - Full Inst Under 3K'!AC2:AC10000,'Removed - Full Inst Under 3K'!L2:L10000,"<>") -> 156875.76
A10: Original Bid List Total | B10: =B7+B9 -> 1238 | C10: =C7+C9 -> 9483828.8
A12: Flags in revised list
A13: 2024 comment "DNB-Open Sold Taxes" (Revised Non-Commercial) | B13: =COUNTIFS('Revised Non-Commercial'!F2:F10000,"DNB*") -> 8 | C13: =SUMIFS('Revised Non-Commercial'!AC2:AC10000,'Revised Non-Commercial'!F2:F10000,"DNB*") -> 57415.35
A14: 2024 comment "DNB-Open Sold Taxes" (Commercial) | B14: =COUNTIFS(Commercial!F2:F10000,"DNB*") -> 0 | C14: =SUMIFS(Commercial!AC2:AC10000,Commercial!F2:F10000,"DNB*") -> 0

Sheet Revised Non-Commercial
A1: Ok to Buy | B1: Do Not Buy | C1: TempBid | D1: Bid | E1: Comment | F1: 2024Comment | G1: 2024Bid | H1: 2023OkToBuy | I1: 2023DoNotBuy | J1: 2023Comment | K1: Taxpayer Name | L1: Parcel Number | M1: PINNoDashes | N1: Assessed Land | O1: Assessed Bldg | P1: ClassCode | Q1: SaleAmt | R1: SaleDt | S1: MortAmt | T1: MortDt | U1: 2ndMort | V1: 2ndMortDt | W1: Lien | X1: Judgmt | Y1: Property Address 1 | Z1: Property City | AA1: Back Tax | AB1: TotalTaxBilled | AC1: Judgment Amount | AD1: HalfInstallment
A2: =TRUE() -> TRUE | B2: =FALSE() -> FALSE | C2: 2 | G2: 3 | H2: =FALSE() -> FALSE | I2: =FALSE() -> FALSE | K2: PATEL INDIRA | L2: 01-01-205-018 | M2: 0101205018 | N2: 19344 | O2: 78179 | P2: 40 - Residential Improvements | Q2: 143500 | R2: 34898 | W2: N | X2: N | Y2: 1634 OAK ST | Z2: HANOVER PARK | AA2: 0 | AB2: 7474.54 | AC2: 7989.07 | AD2: =FALSE() -> FALSE
A3: =TRUE() -> TRUE | B3: =FALSE() -> FALSE | C3: 2 | H3: =FALSE() -> FALSE | I3: =FALSE() -> FALSE | K3: GRAVINA VINCENZO | L3: 01-01-425-032 | M3: 0101425032 | N3: 17999 | O3: 63222 | P3: 40 - Residential Improvements | Q3: 130000 | R3: 35107 | W3: N | X3: N | Y3: 1239 DUNAMON DR | Z3: BARTLETT | AA3: 0 | AB3: 6566.96 | AC3: 3441.24 | AD3: =TRUE() -> TRUE
A4: =TRUE() -> TRUE | B4: =FALSE() -> FALSE | C4: 3 | H4: =FALSE() -> FALSE | I4: =FALSE() -> FALSE | K4: KENNEDY MICHAEL | L4: 01-02-200-012 | M4: 0102200012 | N4: 34212 | O4: 88198 | P4: 40 - Residential Improvements | Q4: 185000 | R4: 43894 | W4: N | X4: Y | Y4: 716 BALBOA TER W | Z4: BARTLETT | AA4: 0 | AB4: 9897.22 | AC4: 10575.28 | AD4: =FALSE() -> FALSE
A5: =TRUE() -> TRUE | B5: =FALSE() -> FALSE | C5: 2 | H5: =FALSE() -> FALSE | I5: =FALSE() -> FALSE | K5: CABRAL PORFIRIO & F P | L5: 01-02-201-129 | M5: 0102201129 | N5: 33915 | O5: 77606 | P5: 40 - Residential Improvements | S5: 186000 | T5: 38335 | W5: N | X5: N | Y5: 446 HARBOR TER | Z5: BARTLETT | AA5: 0 | AB5: 7723.16 | AC5: 4045.35 | AD5: =TRUE() -> TRUE
A6: =TRUE() -> TRUE | B6: =FALSE() -> FALSE | C6: 2 | H6: =FALSE() -> FALSE | I6: =FALSE() -> FALSE | K6: SHAHY LLC | L6: 01-02-203-010 | M6: 0102203010 | N6: 33992 | O6: 77992 | P6: 40 - Residential Improvements | Q6: 290000 | R6: 45729 | W6: N | X6: N | Y6: 742 VOYAGER DR | Z6: BARTLETT | AA6: 0 | AB6: 8407.42 | AC6: 8984.92 | AD6: =FALSE() -> FALSE
A7: =TRUE() -> TRUE | B7: =FALSE() -> FALSE | C7: 3 | G7: 2 | H7: =TRUE() -> TRUE | I7: =FALSE() -> FALSE | K7: KOHL SCOTT & ANDREA | L7: 01-02-414-012 | M7: 0102414012 | N7: 36340 | O7: 95704 | P7: 40 - Residential Improvements | Q7: 339000 | R7: 38692 | S7: 252000 | T7: 40617 | W7: N | X7: Y | Y7: 951 TALLGRASS DR | Z7: BARTLETT | AA7: 0 | AB7: 10029.34 | AC7: 10716.32 | AD7: =FALSE() -> FALSE
A8: =TRUE() -> TRUE | B8: =FALSE() -> FALSE | C8: 3 | G8: 3 | H8: =TRUE() -> TRUE | I8: =FALSE() -> FALSE | K8: MILLER JONATHAN & JAMIE | L8: 01-03-104-017 | M8: 0103104017 | N8: 53975 | O8: 120559 | P8: 40 - Residential Improvements | Q8: 355000 | R8: 37847 | W8: N | X8: Y | Y8: 707 BRAINTREE LN | Z8: BARTLETT | AA8: 0 | AB8: 14111.6 | AC8: 15074.13 | AD8: =FALSE() -> FALSE
A9: =TRUE() -> TRUE | B9: =FALSE() -> FALSE | C9: 2 | H9: =FALSE() -> FALSE | I9: =FALSE() -> FALSE | K9: GABRICH F & T &D GARRICK | L9: 01-03-304-030 | M9: 0103304030 | N9: 36317 | O9: 73869 | P9: 40 - Residential Improvements | Y9: 936 CUYAHOGA TERR | Z9: BARTLETT | AA9: 0 | AB9: 7615.22 | AC9: 3988.95 | AD9: =TRUE() -> TRUE
A10: =TRUE() -> TRUE | B10: =FALSE() -> FALSE | C10: 2 | H10: =TRUE() -> TRUE | I10: =FALSE() -> FALSE | K10: BATOZHYNSKA YANA | L10: 01-09-415-007 | M10: 0109415007 | N10: 39128 | O10: 116988 | P10: 40 - Residential Improvements | Q10: 358000 | R10: 43522 | S10: 334000 | T10: 44145 | W10: N | X10: N | Y10: 1120 THOUSAND OAKS DR | Z10: BARTLETT | AA10: 0 | AB10: 11975.64 | AC10: 6267.27 | AD10: =TRUE() -> TRUE
A11: =TRUE() -> TRUE | B11: =FALSE() -> FALSE | C11: 2 | H11: =FALSE() -> FALSE | I11: =FALSE() -> FALSE | K11: CONCEPCION CARLOS DELA | L11: 01-09-415-022 | M11: 0109415022 | N11: 35149 | O11: 95241 | P11: 40 - Residential Improvements | Q11: 267500 | R11: 42094 | S11: 194000 | T11: 44140 | W11: N | X11: N | Y11: 1189 CHARTER OAKS DR | Z11: BARTLETT | AA11: 0 | AB11: 9895.6 | AC11: 5180.45 | AD11: =TRUE() -> TRUE
A12: =TRUE() -> TRUE | B12: =FALSE() -> FALSE | C12: 3 | H12: =FALSE() -> FALSE | I12: =FALSE() -> FALSE | K12: FARIAS REBECCA & ADELINE | L12: 01-10-102-023 | M12: 0110102023 | N12: 33518 | O12: 65107 | P12: 40 - Residential Improvements | S12: 100000 | T12: 42858 | U12: 46000 | V12: 35822 | W12: N | X12: N | Y12: 968 LAKEWOOD DR | Z12: BARTLETT | AA12: 0 | AB12: 7327.32 | AC12: 7831.91 | AD12: =FALSE() -> FALSE
A13: =TRUE() -> TRUE | B13: =FALSE() -> FALSE | C13: 3 | H13: =TRUE() -> TRUE | I13: =FALSE() -> FALSE | K13: FIEROH NANCY J | L13: 01-10-104-002 | M13: 0110104002 | N13: 36317 | O13: 79667 | P13: 40 - Residential Improvements | Q13: 200000 | R13: 37154 | S13: 62000 | T13: 43034 | W13: N | X13: N | Y13: 835 BRYN MAWR AVE | Z13: BARTLETT | AA13: 0 | AB13: 8084.04 | AC13: 8639.71 | AD13: =FALSE() -> FALSE
A14: =TRUE() -> TRUE | B14: =FALSE() -> FALSE | C14: 2 | H14: =FALSE() -> FALSE | I14: =FALSE() -> FALSE | K14: LOFDAHL SANDRA L & D J | L14: 01-11-109-008 | M14: 0111109008 | N14: 27368 | O14: 121540 | P14: 40 - Residential Improvements | Q14: 392000 | R14: 38917 | S14: 295143 | T14: 40485 | U14: 39191 | V14: 38917 | W14: N | X14: Y | Y14: 985 HUMMINGBIRD WAY # 43/B | Z14: BARTLETT | AA14: 0 | AB14: 11392.84 | AC14: 5962.76 | AD14: =TRUE() -> TRUE
A15: =TRUE() -> TRUE | B15: =FALSE() -> FALSE | C15: 2 | H15: =FALSE() -> FALSE | I15: =FALSE() -> FALSE | K15: ANDRADE ROLANDO | L15: 01-11-200-024 | M15: 0111200024 | N15: 33838 | O15: 70794 | P15: 40 - Residential Improvements | Q15: 144000 | R15: 36172 | W15: N | X15: Y | Y15: 258 JACKSON CT | Z15: BARTLETT | AA15: 0 | AB15: 7812.98 | AC15: 8350.35 | AD15: =FALSE() -> FALSE
A16: =TRUE() -> TRUE | B16: =FALSE() -> FALSE | C16: 2 | H16: =FALSE() -> FALSE | I16: =FALSE() -> FALSE | K16: MIROWSKI RAYMOND | L16: 01-12-107-020 | M16: 0112107020 | N16: 32779 | O16: 55297 | P16: 40 - Residential Improvements | Q16: 279000 | R16: 45380 | W16: N | X16: Y | Y16: 5356 NIVEN LN | Z16: HANOVER PARK | AA16: 0 | AB16: 6705.96 | AC16: 7168.61 | AD16: =FALSE() -> FALSE
A17: =TRUE() -> TRUE | B17: =FALSE() -> FALSE | C17: 3 | H17: =FALSE() -> FALSE | I17: =FALSE() -> FALSE | K17: THAKKAR JIGAR & SHRADDHA | L17: 01-12-210-022 | M17: 0112210022 | N17: 33926 | O17: 83117 | P17: 40 - Residential Improvements | Q17: 221000 | R17: 42530 | S17: 221000 | T17: 42530 | W17: N | X17: N | Y17: 1915 LUCILLE LN | Z17: HANOVER PARK | AA17: 0 | AB17: 9772.28 | AC17: 10441.91 | AD17: =FALSE() -> FALSE
A18: =TRUE() -> TRUE | B18: =FALSE() -> FALSE | C18: 2 | H18: =TRUE() -> TRUE | I18: =FALSE() -> FALSE | K18: MARTINEZ MARTHA E | L18: 01-13-103-059 | M18: 0113103059 | N18: 14825 | O18: 60544 | P18: 40 - Residential Improvements | Q18: 194000 | R18: 44074 | W18: N | X18: N | Y18: 2151 ROB ROY CT | Z18: HANOVER PARK | AA18: 0 | AB18: 5641.82 | AC18: 6032.64 | AD18: =FALSE() -> FALSE
A19: =TRUE() -> TRUE | B19: =FALSE() -> FALSE | C19: 2 | H19: =FALSE() -> FALSE | I19: =FALSE() -> FALSE | K19: JOHNSON ROBERT L | L19: 01-13-104-056 | M19: 0113104056 | N19: 14825 | O19: 60544 | P19: 40 - Residential Improvements | W19: N | X19: N | Y19: 2119 GLASGOW CT | Z19: HANOVER PARK | AA19: 0 | AB19: 4971.86 | AC19: 5317.46 | AD19: =FALSE() -> FALSE
A20: =TRUE() -> TRUE | B20: =FALSE() -> FALSE | C20: 2 | G20: 3 | H20: =FALSE() -> FALSE | I20: =FALSE() -> FALSE | K20: SINGH KAMLA | L20: 01-13-107-028 | M20: 0113107028 | N20: 34345 | O20: 96145 | P20: 40 - Residential Improvements | Q20: 260000 | R20: 39049 | W20: N | X20: Y | Y20: 4695 GREEN BRIDGE LN | Z20: HANOVER PARK | AA20: 0 | AB20: 10927.9 | AC20: 5719.83 | AD20: =TRUE() -> TRUE
A21: =TRUE() -> TRUE | B21: =FALSE() -> FALSE | C21: 2 | H21: =FALSE() -> FALSE | I21: =FALSE() -> FALSE | K21: ROSTRON MICHAEL | L21: 01-13-126-040 | M21: 0113126040 | N21: 13733 | O21: 70882 | P21: 40 - Residential Improvements | Q21: 139500 | R21: 34628 | S21: 142000 | T21: 43647 | U21: 12800 | V21: 37071 | W21: N | X21: Y | Y21: 1628 COLUMBIA CIR # 3 | Z21: BARTLETT | AA21: 0 | AB21: 6194.56 | AC21: 3246.66 | AD21: =TRUE() -> TRUE
A22: =TRUE() -> TRUE | B22: =FALSE() -> FALSE | C22: 2 | H22: =FALSE() -> FALSE | I22: =FALSE() -> FALSE | K22: CHICAGO TITLE LAND TRUST CO | L22: 01-13-213-074 | M22: 0113213074 | N22: 14935 | O22: 58251 | P22: 40 - Residential Improvements | Q22: 100000 | R22: 45636 | W22: N | X22: N | Y22: 4413 BELL LN | Z22: HANOVER PARK | AA22: 0 | AB22: 5294.98 | AC22: 5662.39 | AD22: =FALSE() -> FALSE
A23: =TRUE() -> TRUE | B23: =FALSE() -> FALSE | C23: 2 | H23: =FALSE() -> FALSE | I23: =FALSE() -> FALSE | K23: THAKKAR SANJANA | L23: 01-13-215-043 | M23: 0113215043 | N23: 14935 | O23: 56598 | P23: 40 - Residential Improvements | Q23: 225000 | R23: 44715 | S23: 168750 | T23: 44715 | W23: N | X23: N | Y23: 4723 JEFFERSON ST | Z23: HANOVER PARK | AA23: 0 | AB23: 6623.4 | AC23: 3470.73 | AD23: =TRUE() -> TRUE
A24: =TRUE() -> TRUE | B24: =FALSE() -> FALSE | C24: 2 | H24: =FALSE() -> FALSE | I24: =FALSE() -> FALSE | K24: SMITH BRIAN | L24: 01-13-309-013 | M24: 0113309013 | N24: 31798 | O24: 79744 | P24: 40 - Residential Improvements | Q24: 238000 | R24: 38225 | S24: 190400 | T24: 38300 | U24: 88700 | V24: 38918 | W24: N | X24: Y | Y24: 2284 HARBOR LN | Z24: HANOVER PARK | AA24: 0 | AB24: 8645.04 | AC24: 4527.03 | AD24: =TRUE() -> TRUE
A25: =TRUE() -> TRUE | B25: =FALSE() -> FALSE | C25: 3 | H25: =FALSE() -> FALSE | I25: =FALSE() -> FALSE | K25: PATEL JEETENDRA | L25: 01-13-312-053 | M25: 0113312053 | N25: 34345 | O25: 86490 | P25: 40 - Residential Improvements | Q25: 209000 | R25: 36657 | W25: Y | X25: N | Y25: 4060 PENNSBURY CT | Z25: HANOVER PARK | AA25: 0 | AB25: 10088.88 | AC25: 10779.88 | AD25: =FALSE() -> FALSE
A26: =TRUE() -> TRUE | B26: =FALSE() -> FALSE | C26: 3 | G26: 2 | H26: =FALSE() -> FALSE | I26: =FALSE() -> FALSE | K26: MCINERNEY PATRICK & C A | L26: 01-13-403-064 | M26: 0113403064 | N26: 36417 | O26: 74134 | P26: 40 - Residential Improvements | Q26: 161000 | R26: 35608 | S26: 168000 | T26: 41766 | U26: 10500 | V26: 41856 | W26: Y | X26: N | Y26: 4015 TORONTO CT | Z26: HANOVER PARK | AA26: 0 | AB26: 9495.4 | AC26: 10146.34 | AD26: =FALSE() -> FALSE
A27: =TRUE() -> TRUE | B27: =FALSE() -> FALSE | C27: 3 | H27: =FALSE() -> FALSE | I27: =FALSE() -> FALSE | K27: KIEU CU | L27: 01-13-412-014 | M27: 0113412014 | N27: 36417 | O27: 86666 | P27: 40 - Residential Improvements | Q27: 390000 | R27: 45505 | S27: 195000 | T27: 45505 | W27: N | X27: N | Y27: 1874 PASTORAL LN | Z27: HANOVER PARK | AA27: 0 | AB27: 10655.78 | AC27: 11385.05 | AD27: =FALSE() -> FALSE
A28: =TRUE() -> TRUE | B28: =FALSE() -> FALSE | C28: 3 | H28: =TRUE() -> TRUE | I28: =FALSE() -> FALSE | K28: ELLISON JASON | L28: 01-15-100-010 | M28: 0115100010 | N28: 95010 | O28: 141500 | P28: 40 - Residential Improvements | Q28: 550000 | R28: 42709 | W28: Y | X28: Y | Y28: 29W520 SCHICK RD | Z28: BARTLETT | AA28: 0 | AB28: 15724 | AC28: 16795.37 | AD28: =FALSE() -> FALSE
A29: =TRUE() -> TRUE | B29: =FALSE() -> FALSE | C29: 3 | H29: =FALSE() -> FALSE | I29: =FALSE() -> FALSE | K29: HUBLER JUSTIN & ASHLIE HARPE | L29: 01-18-210-019 | M29: 0118210019 | N29: 40704 | O29: 113681 | P29: 40 - Residential Improvements | Q29: 725000 | R29: 45601 | S29: 580000 | T29: 45601 | W29: N | X29: N | Y29: 32W224 ARMY TRAIL RD | Z29: WAYNE | AA29: 0 | AB29: 10402.84 | AC29: 11115.03 | AD29: =FALSE() -> FALSE
A30: =TRUE() -> TRUE | B30: =FALSE() -> FALSE | C30: 3 | H30: =FALSE() -> FALSE | I30: =FALSE() -> FALSE | K30: KANCHWALA ALI | L30: 01-19-102-027 | M30: 0119102027 | N30: 41762 | O30: 146251 | P30: 40 - Residential Improvements | Q30: 436500 | R30: 37375 | S30: 242500 | T30: 43913 | W30: N | X30: Y | Y30: 2647 BAINBRIDGE BLVD | Z30: WEST CHICAGO | AA30: 0 | AB30: 13726.36 | AC30: 14662.89 | AD30: =FALSE() -> FALSE
A31: =TRUE() -> TRUE | B31: =FALSE() -> FALSE | C31: 3 | G31: 3 | H31: =FALSE() -> FALSE | I31: =FALSE() -> FALSE | K31: PATEL SAMEERKUMAR & J & L | L31: 01-19-302-043 | M31: 0119302043 | N31: 37398 | O31: 101458 | P31: 40 - Residential Improvements | Q31: 4042000 | R31: 44887 | S31: 390630 | T31: 45350 | W31: N | X31: N | Y31: 2599 BARNHART ST | Z31: WEST CHICAGO | AA31: 0 | AB31: 9978.04 | AC31: 10661.56 | AD31: =FALSE() -> FALSE
A32: =TRUE() -> TRUE | B32: =FALSE() -> FALSE | C32: 3 | H32: =FALSE() -> FALSE | I32: =FALSE() -> FALSE | K32: AVILA MARTIN & B REYES | L32: 01-19-307-025 | M32: 0119307025 | N32: 37398 | O32: 94580 | P32: 40 - Residential Improvements | Q32: 262000 | R32: 41379 | S32: 180000 | T32: 45408 | W32: N | X32: N | Y32: 2915 CULVER LN | Z32: WEST CHICAGO | AA32: 0 | AB32: 9453.58 | AC32: 10101.7 | AD32: =FALSE() -> FALSE
A33: =TRUE() -> TRUE | B33: =FALSE() -> FALSE | C33: 3 | G33: 3 | H33: =FALSE() -> FALSE | I33: =FALSE() -> FALSE | K33: MOTTASHED ELIZABETH | L33: 01-20-406-006 | M33: 0120406006 | N33: 54482 | O33: 212614 | P33: 40 - Residential Improvements | Q33: 695000 | R33: 37260 | S33: 450000 | T33: 37260 | W33: N | X33: Y | Y33: 31W181 PRAIRIE LN | Z33: WAYNE | AA33: 0 | AB33: 19805.82 | AC33: 21152.71 | AD33: =FALSE() -> FALSE
A34: =TRUE() -> TRUE | B34: =FALSE() -> FALSE | C34: 3 | H34: =FALSE() -> FALSE | I34: =FALSE() -> FALSE | K34: EVANS FLEM E & DONNA | L34: 01-20-407-006 | M34: 0120407006 | N34: 67190 | O34: 187661 | P34: 40 - Residential Improvements | R34: 37861 | S34: 442000 | T34: 44321 | W34: N | X34: N | Y34: 4N050 LAKE ELEANOR CT | Z34: WAYNE | AA34: 0 | AB34: 18258.26 | AC34: 19500.69 | AD34: =FALSE() -> FALSE
A35: =TRUE() -> TRUE | B35: =FALSE() -> FALSE | C35: 2 | G35: 2 | H35: =FALSE() -> FALSE | I35: =FALSE() -> FALSE | K35: MATUSZEWSKI BEATA & G | L35: 01-23-411-004 | M35: 0123411004 | N35: 14670 | O35: 72734 | P35: 40 - Residential Improvements | Q35: 134500 | R35: 36725 | W35: N | X35: N | Y35: 1164 ROBIN DR | Z35: CAROL STREAM | AA35: 0 | AB35: 6087.52 | AC35: 6508.43 | AD35: =FALSE() -> FALSE
A36: =TRUE() -> TRUE | B36: =FALSE() -> FALSE | C36: 2 | G36: 2 | H36: =FALSE() -> FALSE | I36: =FALSE() -> FALSE | K36: STROLE MICHELLE | L36: 01-23-411-012 | M36: 0123411012 | N36: 14670 | O36: 76592 | P36: 40 - Residential Improvements | Q36: 231000 | R36: 43789 | W36: N | X36: N | Y36: 1186 ROBIN DR | Z36: CAROL STREAM | AA36: 0 | AB36: 6383.28 | AC36: 6824.15 | AD36: =FALSE() -> FALSE
A37: =TRUE() -> TRUE | B37: =FALSE() -> FALSE | C37: 2 | H37: =FALSE() -> FALSE | I37: =FALSE() -> FALSE | K37: KAMALIA MANOJ P & MANJU | L37: 01-24-107-018 | M37: 0124107018 | N37: 14847 | O37: 62781 | P37: 40 - Residential Improvements | S37: 20000 | T37: 35947 | W37: N | X37: N | Y37: 3901 SPRINGLAKE DR | Z37: HANOVER PARK | AA37: 0 | AB37: 6481.4 | AC37: 3396.53 | AD37: =TRUE() -> TRUE
A38: =TRUE() -> TRUE | B38: =FALSE() -> FALSE | C38: 2 | H38: =FALSE() -> FALSE | I38: =FALSE() -> FALSE | K38: ROMAN ANTONIO & VERONICA | L38: 01-24-113-032 | M38: 0124113032 | N38: 14847 | O38: 71687 | P38: 40 - Residential Improvements | Q38: 155000 | R38: 37533 | S38: 124000 | T38: 37533 | W38: Y | X38: N | Y38: 2112 WINDWARD LN | Z38: HANOVER PARK | AA38: 0 | AB38: 6368.36 | AC38: 3337.47 | AD38: =TRUE() -> TRUE
A39: =TRUE() -> TRUE | B39: =FALSE() -> FALSE | C39: 3 | G39: 2 | H39: =TRUE() -> TRUE | I39: =FALSE() -> FALSE | K39: WEST SUBURBAN BK 14147 | L39: 01-24-116-004 | M39: 0124116004 | N39: 13921 | O39: 69846 | P39: 40 - Residential Improvements | S39: 60000 | T39: 38085 | W39: N | X39: Y | Y39: 1323 GLOUCESTER CIR | Z39: CAROL STREAM | AA39: 0 | AB39: 5808.68 | AC39: 6210.77 | AD39: =FALSE() -> FALSE
A40: =TRUE() -> TRUE | B40: =FALSE() -> FALSE | C40: 2 | H40: =FALSE() -> FALSE | I40: =FALSE() -> FALSE | K40: NAWAB SYED & G SULTANA | L40: 01-24-118-014 | M40: 0124118014 | N40: 38213 | O40: 98085 | P40: 40 - Residential Improvements | Q40: 217500 | R40: 36699 | S40: 211000 | T40: 38026 | W40: N | X40: N | Y40: 1304 WOODLAKE DR | Z40: CAROL STREAM | AA40: 0 | AB40: 9835.96 | AC40: 5149.29 | AD40: =TRUE() -> TRUE
A41: =TRUE() -> TRUE | B41: =FALSE() -> FALSE | C41: 2 | H41: =FALSE() -> FALSE | I41: =FALSE() -> FALSE | K41: MIELE MARY A | L41: 01-24-126-028 | M41: 0124126028 | N41: 16125 | O41: 85939 | P41: 40 - Residential Improvements | Q41: 352000 | R41: 45204 | W41: N | X41: N | Y41: 1043 RIDGEFIELD CIR | Z41: CAROL STREAM | AA41: 0 | AB41: 7381.2 | AC41: 7889.43 | AD41: =FALSE() -> FALSE
A42: =TRUE() -> TRUE | B42: =FALSE() -> FALSE | C42: 2 | H42: =FALSE() -> FALSE | I42: =FALSE() -> FALSE | K42: INTAL ELVIRA | L42: 01-24-127-005 | M42: 0124127005 | N42: 16125 | O42: 78774 | P42: 40 - Residential Improvements | Q42: 160000 | R42: 40925 | S42: 58000 | T42: 43073 | W42: N | X42: N | Y42: 1098 RIDGEFIELD CIR | Z42: CAROL STREAM | AA42: 0 | AB42: 7452.82 | AC42: 3904.1 | AD42: =TRUE() -> TRUE
A43: =TRUE() -> TRUE | B43: =FALSE() -> FALSE | C43: 2 | H43: =TRUE() -> TRUE | I43: =FALSE() -> FALSE | K43: STAUNTON CHRISTINE | L43: 01-24-127-051 | M43: 0124127051 | N43: 16125 | O43: 75049 | P43: 40 - Residential Improvements | Q43: 294000 | R43: 45125 | W43: N | X43: N | Y43: 1252 LAKE SHORE DR | Z43: CAROL STREAM | AA43: 0 | AB43: 7133.34 | AC43: 7624.84 | AD43: =FALSE() -> FALSE
A44: =TRUE() -> TRUE | B44: =FALSE() -> FALSE | C44: 3 | H44: =FALSE() -> FALSE | I44: =FALSE() -> FALSE | K44: GANDHI NISCHAL H & PRIYA | L44: 01-24-203-011 | M44: 0124203011 | N44: 14847 | O44: 66959 | P44: 40 - Residential Improvements | Q44: 106000 | R44: 41239 | S44: 120000 | T44: 43433 | W44: N | X44: N | Y44: 3955 NAUTILUS LN | Z44: HANOVER PARK | AA44: 0 | AB44: 7574.6 | AC44: 8095.89 | AD44: =FALSE() -> FALSE
A45: =TRUE() -> TRUE | B45: =FALSE() -> FALSE | C45: 2 | G45: 3 | H45: =FALSE() -> FALSE | I45: =FALSE() -> FALSE | K45: RUSEF RAMSEY | L45: 01-24-216-013 | M45: 0124216013 | N45: 31798 | O45: 79744 | P45: 40 - Residential Improvements | R45: 45924 | W45: N | X45: N | Y45: 1680 NAUTILUS LN | Z45: HANOVER PARK | AA45: 0 | AB45: 8846.42 | AC45: 9453.55 | AD45: =FALSE() -> FALSE
A46: =TRUE() -> TRUE | B46: =FALSE() -> FALSE | C46: 3 | H46: =TRUE() -> TRUE | I46: =FALSE() -> FALSE | K46: SINGH FAM TR CECIL&KAMLA | L46: 01-24-409-001 | M46: 0124409001 | N46: 38720 | O46: 78884 | P46: 40 - Residential Improvements | W46: N | X46: Y | Y46: 1137 COUNTRY GLEN LN | Z46: CAROL STREAM | AA46: 0 | AB46: 9400.08 | AC46: 10044.58 | AD46: =FALSE() -> FALSE
A47: =TRUE() -> TRUE | B47: =FALSE() -> FALSE | C47: 3 | H47: =FALSE() -> FALSE | I47: =FALSE() -> FALSE | K47: SYED U & M KHUSHTAR | L47: 01-24-415-047 | M47: 0124415047 | N47: 17823 | O47: 74123 | P47: 40 - Residential Improvements | Q47: 210000 | R47: 38195 | S47: 46200 | T47: 39510 | W47: N | X47: N | Y47: 1349 TRINITY DR | Z47: CAROL STREAM | AA47: 0 | AB47: 7885.66 | AC47: 8427.94 | AD47: =FALSE() -> FALSE
A48: =TRUE() -> TRUE | B48: =FALSE() -> FALSE | C48: 2 | H48: =FALSE() -> FALSE | I48: =FALSE() -> FALSE | K48: PATEL NIRAV & MITTAL | L48: 01-24-416-024 | M48: 0124416024 | N48: 17823 | O48: 76294 | P48: 40 - Residential Improvements | Q48: 660 | R48: 43091 | S48: 160000 | T48: 44153 | W48: N | X48: N | Y48: 778 TRINITY CT | Z48: CAROL STREAM | AA48: 0 | AB48: 7385.74 | AC48: 3869.05 | AD48: =TRUE() -> TRUE
A49: =TRUE() -> TRUE | B49: =FALSE() -> FALSE | C49: 2 | H49: =FALSE() -> FALSE | I49: =FALSE() -> FALSE | K49: GORA DANIEL W | L49: 01-25-201-021 | M49: 0125201021 | N49: 35744 | O49: 78554 | P49: 40 - Residential Improvements | W49: N | X49: N | Y49: 987 VALLEY VIEW TR | Z49: CAROL STREAM | AA49: 0 | AB49: 8430.44 | AC49: 4414.9 | AD49: =TRUE() -> TRUE
A50: =TRUE() -> TRUE | B50: =FALSE() -> FALSE | C50: 2 | H50: =FALSE() -> FALSE | I50: =FALSE() -> FALSE | K50: MARYEA A & B MELESAW | L50: 01-25-406-010 | M50: 0125406010 | N50: 34565 | O50: 85409 | P50: 40 - Residential Improvements | Q50: 205000 | R50: 41578 | S50: 219300 | T50: 44041 | W50: N | X50: N | Y50: 582 PONTIAC LN | Z50: CAROL STREAM | AA50: 0 | AB50: 9630.56 | AC50: 5041.97 | AD50: =TRUE() -> TRUE
A51: =TRUE() -> TRUE | B51: =FALSE() -> FALSE | C51: 2 | H51: =FALSE() -> FALSE | I51: =FALSE() -> FALSE | K51: NGUYEN HUY V | L51: 01-25-409-012 | M51: 0125409012 | N51: 13932 | O51: 60676 | P51: 40 - Residential Improvements | R51: 43822 | W51: N | X51: Y | Y51: 551 ALTON CT | Z51: CAROL STREAM | AA51: 0 | AB51: 5712.56 | AC51: 2994.81 | AD51: =TRUE() -> TRUE
A52: =TRUE() -> TRUE | B52: =FALSE() -> FALSE | C52: 2 | G52: 3 | H52: =FALSE() -> FALSE | I52: =FALSE() -> FALSE | K52: GANLEY-LIEBICH MARIE | L52: 01-26-401-034 | M52: 0126401034 | N52: 44815 | O52: 183748 | P52: 40 - Residential Improvements | Q52: 620000 | R52: 44365 | W52: N | X52: N | Y52: 627 CHRISTOPHER LN | Z52: CAROL STREAM | AA52: 0 | AB52: 18969.98 | AC52: 9921.81 | AD52: =TRUE() -> TRUE
A53: =TRUE() -> TRUE | B53: =FALSE() -> FALSE | C53: 2 | H53: =FALSE() -> FALSE | I53: =FALSE() -> FALSE | K53: PLUTOLUNA LLC | L53: 01-28-103-019 | M53: 0128103019 | N53: 45367 | O53: 172880 | P53: 40 - Residential Improvements | Y53: 3N631 LAKEVIEW CT | Z53: WEST CHICAGO | AA53: 0 | AB53: 14804.58 | AC53: 7745.39 | AD53: =TRUE() -> TRUE
A54: =TRUE() -> TRUE | B54: =FALSE() -> FALSE | C54: 3 | H54: =FALSE() -> FALSE | I54: =FALSE() -> FALSE | K54: EVANS FLEM D & DONNA L | L54: 01-28-201-011 | M54: 0128201011 | N54: 33606 | O54: 119974 | P54: 40 - Residential Improvements | Q54: 40500 | R54: 35069 | W54: N | X54: N | Y54: 3N752 LOCUST AVE | Z54: WEST CHICAGO | AA54: 0 | AB54: 10825.1 | AC54: 11565.79 | AD54: =FALSE() -> FALSE
A55: =TRUE() -> TRUE | B55: =FALSE() -> FALSE | C55: 2 | H55: =FALSE() -> FALSE | I55: =FALSE() -> FALSE | K55: EVANS FLEM & DONNA | L55: 01-28-401-036 | M55: 0128401036 | N55: 34411 | O55: 67752 | P55: 40 - Residential Improvements | Q55: 330000 | R55: 44483 | W55: N | X55: N | Y55: 2080 ARAPAHO DR | Z55: WEST CHICAGO | AA55: 0 | AB55: 9025.06 | AC55: 9644.25 | AD55: =FALSE() -> FALSE
A56: =TRUE() -> TRUE | B56: =FALSE() -> FALSE | C56: 2 | H56: =TRUE() -> TRUE | I56: =FALSE() -> FALSE | K56: NIKU REAL ESTATE LLC | L56: 01-30-103-013 | M56: 0130103013 | N56: 19696 | O56: 70067 | P56: 40 - Residential Improvements | Q56: 192500 | R56: 40059 | W56: Y | X56: Y | Y56: 511 PHEASANT TR | Z56: ST CHARLES | AA56: 0 | AB56: 5938.7 | AC56: 3112.97 | AD56: =TRUE() -> TRUE
A57: =TRUE() -> TRUE | B57: =FALSE() -> FALSE | C57: 2 | G57: 3 | H57: =FALSE() -> FALSE | I57: =FALSE() -> FALSE | K57: BANDUCCI LUIGI & MARIA | L57: 01-30-103-016 | M57: 0130103016 | N57: 19696 | O57: 68325 | P57: 40 - Residential Improvements | Q57: 207000 | R57: 37075 | W57: Y | X57: Y | Y57: 505 PHEASANT TRL | Z57: ST CHARLES | AA57: 0 | AB57: 5812.16 | AC57: 6214.48 | AD57: =FALSE() -> FALSE
A58: =TRUE() -> TRUE | B58: =FALSE() -> FALSE | C58: 2 | G58: 2 | H58: =TRUE() -> TRUE | I58: =FALSE() -> FALSE | K58: MC INTOSH THOMAS | L58: 01-30-105-017 | M58: 0130105017 | N58: 23653 | O58: 85189 | P58: 40 - Residential Improvements | Q58: 780000 | R58: 44970 | W58: N | X58: N | Y58: 670 PHEASANT TRL | Z58: ST CHARLES | AA58: 0 | AB58: 7324.46 | AC58: 7828.86 | AD58: =FALSE() -> FALSE
A59: =TRUE() -> TRUE | B59: =FALSE() -> FALSE | C59: 2 | H59: =FALSE() -> FALSE | I59: =FALSE() -> FALSE | K59: RAMOS REYSON CARLO | L59: 01-33-204-016 | M59: 0133204016 | N59: 34135 | O59: 115037 | P59: 40 - Residential Improvements | Q59: 535000 | R59: 45897 | S59: 525309 | T59: 45897 | W59: N | X59: Y | Y59: 1409 SNOWBERRY LN | Z59: WEST CHICAGO | AA59: 0 | AB59: 12471.16 | AC59: 6526.18 | AD59: =TRUE() -> TRUE
A60: =TRUE() -> TRUE | B60: =FALSE() -> FALSE | C60: 2 | H60: =FALSE() -> FALSE | I60: =FALSE() -> FALSE | K60: GAUTAM NEEL & PREKSHA | L60: 01-33-416-004 | M60: 0133416004 | N60: 13987 | O60: 69802 | P60: 40 - Residential Improvements | Q60: 210000 | R60: 38657 | W60: N | X60: N | Y60: 123 TARA LN | Z60: WEST CHICAGO | AA60: 0 | AB60: 6695.22 | AC60: 7157.14 | AD60: =FALSE() -> FALSE
A61: =TRUE() -> TRUE | B61: =FALSE() -> FALSE | C61: 2 | H61: =FALSE() -> FALSE | I61: =FALSE() -> FALSE | K61: FLORIAN NANCY | L61: 01-35-200-006 | M61: 0135200006 | N61: 37508 | O61: 107442 | P61: 40 - Residential Improvements | R61: 44792 | W61: N | X61: N | Y61: 2N721 FAIR OAKS RD | Z61: WEST CHICAGO | AA61: 0 | AB61: 7048.84 | AC61: 7534.64 | AD61: =FALSE() -> FALSE
A62: =TRUE() -> TRUE | B62: =FALSE() -> FALSE | C62: 2 | H62: =FALSE() -> FALSE | I62: =FALSE() -> FALSE | K62: RITCHIE SHARON | L62: 01-35-303-003 | M62: 0135303003 | N62: 39525 | O62: 107674 | P62: 40 - Residential Improvements | Q62: 546000 | R62: 45642 | W62: N | X62: N | Y62: 28W681 INDIAN KNOLL RD | Z62: WEST CHICAGO | AA62: 0 | AB62: 11223.56 | AC62: 5874.31 | AD62: =TRUE() -> TRUE
A63: =TRUE() -> TRUE | B63: =FALSE() -> FALSE | C63: 2 | H63: =FALSE() -> FALSE | I63: =FALSE() -> FALSE | K63: DAVEY ALICIA | L63: 01-36-200-012 | M63: 0136200012 | N63: 80185 | O63: 111201 | P63: 40 - Residential Improvements | S63: 179000 | T63: 44498 | W63: N | X63: N | Y63: 2N600 JEFFERSON ST | Z63: WEST CHICAGO | AA63: 0 | AB63: 13970.16 | AC63: 7309.41 | AD63: =TRUE() -> TRUE
A64: =TRUE() -> TRUE | B64: =FALSE() -> FALSE | C64: 2 | H64: =FALSE() -> FALSE | I64: =FALSE() -> FALSE | K64: KERTH DAN P | L64: 01-36-202-096 | M64: 0136202096 | N64: 13932 | O64: 52266 | P64: 40 - Residential Improvements | Q64: 100000 | R64: 41446 | W64: N | X64: N | Y64: 506 DAKOTA CT | Z64: CAROL STREAM | AA64: 0 | AB64: 4305.18 | AC64: 2259.46 | AD64: =TRUE() -> TRUE
A65: =TRUE() -> TRUE | B65: =FALSE() -> FALSE | C65: 2 | H65: =FALSE() -> FALSE | I65: =FALSE() -> FALSE | K65: OBERJAT FRANZ &ANNELIESE | L65: 01-36-202-110 | M65: 0136202110 | N65: 13932 | O65: 52586 | P65: 40 - Residential Improvements | W65: N | X65: N | Y65: 815 TEXAS CT | Z65: CAROL STREAM | AA65: 0 | AB65: 4332.64 | AC65: 4635.09 | AD65: =FALSE() -> FALSE
A66: =TRUE() -> TRUE | B66: =FALSE() -> FALSE | C66: 3 | H66: =FALSE() -> FALSE | I66: =FALSE() -> FALSE | K66: KUKOLJ DUSAN | L66: 02-01-302-001 | M66: 0201302001 | N66: 38076 | O66: 191395 | P66: 40 - Residential Improvements | Q66: 345000 | R66: 44207 | S66: 276000 | T66: 44207 | U66: 83500 | V66: 45595 | W66: N | X66: Y | Y66: 21W665 THORNDALE AVE | Z66: MEDINAH | AA66: 0 | AB66: 12738.34 | AC66: 13608.18 | AD66: =FALSE() -> FALSE
A67: =TRUE() -> TRUE | B67: =FALSE() -> FALSE | C67: 2 | H67: =FALSE() -> FALSE | I67: =FALSE() -> FALSE | K67: ESPINOSA MARIA | L67: 02-02-104-064 | M67: 0202104064 | N67: 15429 | O67: 56184 | P67: 40 - Residential Improvements | Q67: 108000 | R67: 41942 | W67: N | X67: N | Y67: 618 E DEVON AVE | Z67: ROSELLE | AA67: 0 | AB67: 4573.56 | AC67: 4892.28 | AD67: =FALSE() -> FALSE
A68: =TRUE() -> TRUE | B68: =FALSE() -> FALSE | C68: 3 | H68: =FALSE() -> FALSE | I68: =FALSE() -> FALSE | K68: ESPINOSA MARIA | L68: 02-02-104-065 | M68: 0202104065 | N68: 15429 | O68: 72772 | P68: 40 - Residential Improvements | Q68: 230000 | R68: 38937 | S68: 108600 | T68: 41976 | W68: N | X68: N | Y68: 616 E DEVON AVE | Z68: ROSELLE | AA68: 0 | AB68: 4483.38 | AC68: 4796.01 | AD68: =FALSE() -> FALSE
A69: =TRUE() -> TRUE | B69: =FALSE() -> FALSE | C69: 2 | H69: =FALSE() -> FALSE | I69: =FALSE() -> FALSE | K69: WATSON WILLIAM J | L69: 02-02-104-066 | M69: 0202104066 | N69: 15429 | O69: 67163 | P69: 40 - Residential Improvements | S69: 102500 | T69: 43675 | W69: N | X69: N | Y69: 614 E DEVON AVE | Z69: ROSELLE | AA69: 0 | AB69: 4636.1 | AC69: 2432.36 | AD69: =TRUE() -> TRUE
A70: =TRUE() -> TRUE | B70: =FALSE() -> FALSE | C70: 2 | H70: =FALSE() -> FALSE | I70: =FALSE() -> FALSE | K70: KRIEPKE ANGELA | L70: 02-02-104-099 | M70: 0202104099 | N70: 15429 | O70: 60995 | P70: 40 - Residential Improvements | Q70: 195000 | R70: 43909 | S70: 191468 | T70: 43909 | U70: 47421.44 | V70: 44922 | W70: N | X70: Y | Y70: 676 CIRCLE DR | Z70: ROSELLE | AA70: 0 | AB70: 4369.9 | AC70: 2293.27 | AD70: =TRUE() -> TRUE
A71: =TRUE() -> TRUE | B71: =FALSE() -> FALSE | C71: 2 | G71: 3 | H71: =FALSE() -> FALSE | I71: =FALSE() -> FALSE | K71: ESPINOSA MARIA | L71: 02-02-104-139 | M71: 0202104139 | N71: 15429 | O71: 60908 | P71: 40 - Residential Improvements | Q71: 147500 | R71: 42234 | W71: N | X71: N | Y71: 671 CIRCLE DR | Z71: ROSELLE | AA71: 0 | AB71: 4875.26 | AC71: 5214.34 | AD71: =FALSE() -> FALSE
A72: =TRUE() -> TRUE | B72: =FALSE() -> FALSE | C72: 2 | H72: =FALSE() -> FALSE | I72: =FALSE() -> FALSE | K72: WERR ROBERT M | L72: 02-02-106-053 | M72: 0202106053 | N72: 30651 | O72: 74828 | P72: 40 - Residential Improvements | Q72: 137500 | R72: 33856 | W72: N | X72: N | Y72: 624 E GRANVILLE AVE | Z72: ROSELLE | AA72: 0 | AB72: 6225.5 | AC72: 6655.72 | AD72: =FALSE() -> FALSE
A73: =TRUE() -> TRUE | B73: =FALSE() -> FALSE | C73: 2 | H73: =FALSE() -> FALSE | I73: =FALSE() -> FALSE | K73: ATG TRUST | L73: 02-02-306-016 | M73: 0202306016 | N73: 44024 | O73: 153735 | P73: 40 - Residential Improvements | R73: 43836 | W73: N | X73: N | Y73: 427 LOCUST LN | Z73: ROSELLE | AA73: 0 | AB73: 14259.82 | AC73: 7460.76 | AD73: =TRUE() -> TRUE
A74: =TRUE() -> TRUE | B74: =FALSE() -> FALSE | C74: 2 | G74: 3 | H74: =FALSE() -> FALSE | I74: =FALSE() -> FALSE | K74: O BRIEN TIMOTHY J | L74: 02-02-315-069 | M74: 0202315069 | N74: 16621 | O74: 66758 | P74: 40 - Residential Improvements | R74: 45510 | W74: N | X74: N | Y74: 5 TERRY DR # A | Z74: ROSELLE | AA74: 0 | AB74: 4303.18 | AC74: 2258.41 | AD74: =TRUE() -> TRUE
A75: =TRUE() -> TRUE | B75: =FALSE() -> FALSE | C75: 2 | G75: 3 | H75: =FALSE() -> FALSE | I75: =FALSE() -> FALSE | K75: RICO CARMEN | L75: 02-02-334-002 | M75: 0202334002 | N75: 16621 | O75: 40798 | P75: 40 - Residential Improvements | R75: 43549 | W75: N | X75: N | Y75: 38 TERRY DR # B | Z75: ROSELLE | AA75: 0 | AB75: 3667.08 | AC75: 1926.05 | AD75: =TRUE() -> TRUE
A76: =TRUE() -> TRUE | B76: =FALSE() -> FALSE | C76: 3 | H76: =FALSE() -> FALSE | I76: =FALSE() -> FALSE | K76: GORNY WALLY & URSULA | L76: 02-03-100-008 | M76: 0203100008 | N76: 38808 | O76: 161324 | P76: 40 - Residential Improvements | R76: 45218 | W76: N | X76: Y | Y76: 370 THOROUGHBRED LN | Z76: ROSELLE | AA76: 0 | AB76: 14438.14 | AC76: 15422.72 | AD76: =FALSE() -> FALSE
A77: =TRUE() -> TRUE | B77: =FALSE() -> FALSE | C77: 3 | H77: =FALSE() -> FALSE | I77: =FALSE() -> FALSE | K77: ANJUMAN-E-SHUJAEE | L77: 02-03-218-003 | M77: 0203218003 | N77: 39125 | O77: 137081 | P77: 40 - Residential Improvements | Q77: 502000 | R77: 44694 | W77: N | X77: N | Y77: 341 AMBLESIDE DR | Z77: ROSELLE | AA77: 0 | AB77: 12640.18 | AC77: 13503.39 | AD77: =FALSE() -> FALSE
A78: =TRUE() -> TRUE | B78: =FALSE() -> FALSE | C78: 3 | H78: =TRUE() -> TRUE | I78: =FALSE() -> FALSE | K78: TYBOROWICZ WOJCIECH | L78: 02-03-221-003 | M78: 0203221003 | N78: 16206 | O78: 45993 | P78: 40 - Residential Improvements | Q78: 230000 | R78: 44798 | S78: 183920 | T78: 44798 | W78: N | X78: N | Y78: 57 E HATTENDORF AVE # 401 | Z78: ROSELLE | AA78: 0 | AB78: 4072.88 | AC78: 4357.8 | AD78: =FALSE() -> FALSE
A79: =TRUE() -> TRUE | B79: =FALSE() -> FALSE | C79: 2 | H79: =FALSE() -> FALSE | I79: =FALSE() -> FALSE | K79: GURVITS ARFENYA G | L79: 02-03-222-016 | M79: 0203222016 | N79: 17113 | O79: 76687 | P79: 40 - Residential Improvements | Q79: 250000 | R79: 44894 | W79: N | X79: N | Y79: 100 N BOKELMAN ST # 325 | Z79: ROSELLE | AA79: 0 | AB79: 6447.62 | AC79: 6892.83 | AD79: =FALSE() -> FALSE
A80: =TRUE() -> TRUE | B80: =FALSE() -> FALSE | C80: 2 | H80: =FALSE() -> FALSE | I80: =FALSE() -> FALSE | K80: GIZZI ROSE MARIE | L80: 02-03-222-074 | M80: 0203222074 | N80: 17113 | O80: 74774 | P80: 40 - Residential Improvements | R80: 42391 | S80: 50000 | T80: 43357 | W80: N | X80: N | Y80: 50 N BOKELMAN ST # 339 | Z80: ROSELLE | AA80: 0 | AB80: 4349.5 | AC80: 2282.61 | AD80: =TRUE() -> TRUE
A81: =TRUE() -> TRUE | B81: =FALSE() -> FALSE | C81: 3 | H81: =FALSE() -> FALSE | I81: =FALSE() -> FALSE | K81: PENA AMY | L81: 02-03-418-025 | M81: 0203418025 | N81: 44002 | O81: 81094 | P81: 40 - Residential Improvements | Q81: 200000 | R81: 44431 | S81: 560000 | T81: 44861 | U81: 70000 | V81: 44862 | W81: N | X81: N | Y81: 315 E PINE AVE | Z81: ROSELLE | AA81: 0 | AB81: 6920.76 | AC81: 7397.91 | AD81: =FALSE() -> FALSE
A82: =TRUE() -> TRUE | B82: =FALSE() -> FALSE | C82: 3 | H82: =FALSE() -> FALSE | I82: =FALSE() -> FALSE | K82: BELLAVIA JOSEPH & SYLVIA | L82: 02-04-300-012 | M82: 0204300012 | N82: 38732 | O82: 90378 | P82: 40 - Residential Improvements | S82: 412800 | T82: 38631 | W82: N | X82: Y | Y82: 980 BORDEN DR | Z82: ROSELLE | AA82: 0 | AB82: 9115.1 | AC82: 9740.37 | AD82: =FALSE() -> FALSE
A83: =TRUE() -> TRUE | B83: =FALSE() -> FALSE | C83: 2 | H83: =TRUE() -> TRUE | I83: =FALSE() -> FALSE | K83: COMMUNITY SAVINGS BK | L83: 02-04-309-089 | M83: 0204309089 | N83: 38732 | O83: 88333 | P83: 40 - Residential Improvements | Q83: 295000 | R83: 37505 | W83: N | X83: N | Y83: 1045 OLYMPIA LN | Z83: ROSELLE | AA83: 0 | AB83: 8961.2 | AC83: 9576.08 | AD83: =FALSE() -> FALSE
A84: =TRUE() -> TRUE | B84: =FALSE() -> FALSE | C84: 2 | H84: =FALSE() -> FALSE | I84: =FALSE() -> FALSE | K84: HUZVAR LADISLAV &MARGITA | L84: 02-04-415-028 | M84: 0204415028 | N84: 40645 | O84: 107185 | P84: 40 - Residential Improvements | Q84: 250000 | R84: 37084 | W84: N | X84: Y | Y84: 410 MERRIMAC CT | Z84: ROSELLE | AA84: 0 | AB84: 6960.12 | AC84: 3646.66 | AD84: =TRUE() -> TRUE
A85: =TRUE() -> TRUE | B85: =FALSE() -> FALSE | C85: 2 | H85: =FALSE() -> FALSE | I85: =FALSE() -> FALSE | K85: NIRTAUT KNEPLER JOANNE | L85: 02-05-219-071 | M85: 0205219071 | N85: 12455 | O85: 56775 | P85: 40 - Residential Improvements | Q85: 265000 | R85: 45468 | W85: N | X85: N | Y85: 1300 WINFIELD CT # 3 | Z85: ROSELLE | AA85: 0 | AB85: 1879.32 | AC85: 991.94 | AD85: =TRUE() -> TRUE
A86: =TRUE() -> TRUE | B86: =FALSE() -> FALSE | C86: 2 | H86: =FALSE() -> FALSE | I86: =FALSE() -> FALSE | K86: PASHKIVSKYY TARAS | L86: 02-05-220-277 | M86: 0205220277 | N86: 21640 | O86: 69240 | P86: 40 - Residential Improvements | Q86: 335000 | R86: 45531 | S86: 268000 | T86: 45531 | W86: N | X86: N | Y86: 161 BRENDON CT | Z86: ROSELLE | AA86: 0 | AB86: 6237.8 | AC86: 3269.25 | AD86: =TRUE() -> TRUE
A87: =TRUE() -> TRUE | B87: =FALSE() -> FALSE | C87: 3 | G87: 2 | H87: =TRUE() -> TRUE | I87: =FALSE() -> FALSE | K87: HUNTINGTON PATRICIA E | L87: 02-05-220-278 | M87: 0205220278 | N87: 21640 | O87: 72882 | P87: 40 - Residential Improvements | Q87: 173500 | R87: 36074 | S87: 200000 | T87: 38090 | W87: Y | X87: Y | Y87: 177 AVALON CT | Z87: ROSELLE | AA87: 0 | AB87: 5909.82 | AC87: 6318.73 | AD87: =FALSE() -> FALSE
A88: =TRUE() -> TRUE | B88: =FALSE() -> FALSE | C88: 3 | H88: =TRUE() -> TRUE | I88: =FALSE() -> FALSE | K88: MERLOS EUGENIA | L88: 02-06-104-169 | M88: 0206104169 | N88: 11044 | O88: 45260 | P88: 40 - Residential Improvements | Q88: 82000 | R88: 36040 | S88: 40000 | T88: 38072 | W88: N | X88: Y | Y88: 1509 SUTTER DR # 43-1 | Z88: HANOVER PARK | AA88: 0 | AB88: 4025.32 | AC88: 4307.03 | AD88: =FALSE() -> FALSE
A89: =TRUE() -> TRUE | B89: =FALSE() -> FALSE | C89: 3 | G89: 2 | H89: =TRUE() -> TRUE | I89: =FALSE() -> FALSE | K89: MCLENNAN B &B &L STEWART | L89: 01-21-405-002 | M89: 0121405002 | N89: 33606 | O89: 80141 | P89: 40 - Residential Improvements | Q89: 147500 | R89: 35244 | S89: 7765 | T89: 35857 | W89: N | X89: N | Y89: 4N141 LOCUST AVE | Z89: WEST CHICAGO | AA89: 0 | AB89: 6889.7 | AC89: 7364.76 | AD89: =FALSE() -> FALSE
A90: =TRUE() -> TRUE | B90: =FALSE() -> FALSE | C90: 3 | H90: =TRUE() -> TRUE | I90: =FALSE() -> FALSE | K90: CHICAGO TITLE 8002372154 | L90: 01-21-405-005 | M90: 0121405005 | N90: 33606 | O90: 68744 | P90: 40 - Residential Improvements | Q90: 210000 | R90: 40648 | S90: 157475 | T90: 42727 | W90: Y | X90: Y | Y90: 4N091 LOCUST AVE | Z90: WEST CHICAGO | AA90: 0 | AB90: 6650.26 | AC90: 7109.15 | AD90: =FALSE() -> FALSE
A91: =TRUE() -> TRUE | B91: =FALSE() -> FALSE | C91: 2 | H91: =FALSE() -> FALSE | I91: =FALSE() -> FALSE | K91: PATEL KETAN | L91: 01-22-100-038 | M91: 0122100038 | N91: 53820 | O91: 154187 | P91: 40 - Residential Improvements | Q91: 435000 | R91: 43172 | S91: 390000 | T91: 43573 | U91: 46000 | V91: 45593 | W91: N | X91: N | Y91: 4N714 TURNMILL LN | Z91: WEST CHICAGO | AA91: 0 | AB91: 13209.88 | AC91: 6912.16 | AD91: =TRUE() -> TRUE
A92: =TRUE() -> TRUE | B92: =FALSE() -> FALSE | C92: 2 | H92: =FALSE() -> FALSE | I92: =FALSE() -> FALSE | K92: FAST FINANCIAL CORP | L92: 02-06-104-233 | M92: 0206104233 | N92: 11044 | O92: 52718 | P92: 40 - Residential Improvements | R92: 42103 | W92: N | X92: Y | Y92: 1448 BEAR FLAG DR | Z92: HANOVER PARK | AA92: 0 | AB92: 5313.48 | AC92: 5682.14 | AD92: =FALSE() -> FALSE
A93: =TRUE() -> TRUE | B93: =FALSE() -> FALSE | C93: 2 | H93: =FALSE() -> FALSE | I93: =FALSE() -> FALSE | K93: WALLACE LEON | L93: 02-06-104-241 | M93: 0206104241 | N93: 11044 | O93: 49656 | P93: 40 - Residential Improvements | Q93: 125500 | R93: 37533 | W93: N | X93: N | Y93: 1500 BEAR FLAG DR | Z93: HANOVER PARK | AA93: 0 | AB93: 5058.34 | AC93: 5409.78 | AD93: =FALSE() -> FALSE
A94: =TRUE() -> TRUE | B94: =FALSE() -> FALSE | C94: 2 | H94: =FALSE() -> FALSE | I94: =FALSE() -> FALSE | K94: AJA INVESTMENTS LLC | L94: 02-06-105-067 | M94: 0206105067 | N94: 9798 | O94: 47950 | P94: 40 - Residential Improvements | Q94: 35000 | R94: 40486 | W94: N | X94: N | Y94: 1443 SACRAMENTO DR | Z94: HANOVER PARK | AA94: 0 | AB94: 4812.32 | AC94: 2524.44 | AD94: =TRUE() -> TRUE
A95: =TRUE() -> TRUE | B95: =FALSE() -> FALSE | C95: 3 | G95: 2 | H95: =TRUE() -> TRUE | I95: =FALSE() -> FALSE | K95: CASTANEDA YANELI | L95: 02-06-309-018 | M95: 0206309018 | N95: 30454 | O95: 71340 | P95: 40 - Residential Improvements | Q95: 160000 | R95: 43872 | S95: 120000 | T95: 43872 | W95: N | X95: Y | Y95: 5700 UNIT CT | Z95: HANOVER PARK | AA95: 0 | AB95: 7816.14 | AC95: 8353.73 | AD95: =FALSE() -> FALSE
A96: =TRUE() -> TRUE | B96: =FALSE() -> FALSE | C96: 2 | H96: =FALSE() -> FALSE | I96: =FALSE() -> FALSE | K96: GHADIR PROPERTIES LLC | L96: 02-06-405-029 | M96: 0206405029 | N96: 6692 | O96: 55790 | P96: 40 - Residential Improvements | Q96: 69000 | R96: 41984 | W96: N | X96: N | Y96: 5677 COURT TIBURON | Z96: HANOVER PARK | AA96: 0 | AB96: 6151.9 | AC96: 6577.16 | AD96: =FALSE() -> FALSE
A97: =TRUE() -> TRUE | B97: =FALSE() -> FALSE | C97: 2 | H97: =FALSE() -> FALSE | I97: =FALSE() -> FALSE | K97: REID KEVIN E | L97: 02-07-101-017 | M97: 0207101017 | N97: 36053 | O97: 59793 | P97: 40 - Residential Improvements | Q97: 168000 | R97: 37291 | S97: 131000 | T97: 37763 | W97: N | X97: N | Y97: 5506 COOPER CT | Z97: HANOVER PARK | AA97: 0 | AB97: 7320.48 | AC97: 3834.95 | AD97: =TRUE() -> TRUE
A98: =TRUE() -> TRUE | B98: =FALSE() -> FALSE | C98: 2 | H98: =FALSE() -> FALSE | I98: =FALSE() -> FALSE | K98: ADESANYA PHOENIA OLUSESAN | L98: 02-07-204-067 | M98: 0207204067 | N98: 6692 | O98: 61553 | P98: 40 - Residential Improvements | Q98: 197000 | R98: 45202 | W98: N | X98: N | Y98: 5568 CARMEL DR | Z98: HANOVER PARK | AA98: 0 | AB98: 6719.34 | AC98: 7182.9 | AD98: =FALSE() -> FALSE
A99: =TRUE() -> TRUE | B99: =FALSE() -> FALSE | C99: 2 | F99: DNB-Open Sold Taxes | H99: =FALSE() -> FALSE | I99: =FALSE() -> FALSE | K99: SINGH VIRPAL | L99: 02-07-204-075 | M99: 0207204075 | N99: 6692 | O99: 64877 | P99: 40 - Residential Improvements | Q99: 131000 | R99: 39602 | W99: N | X99: Y | Y99: 5581 CARMEL DR | Z99: HANOVER PARK | AA99: 0 | AB99: 7046.62 | AC99: 3691.86 | AD99: =TRUE() -> TRUE
A100: =TRUE() -> TRUE | B100: =FALSE() -> FALSE | C100: 2 | G100: 3 | H100: =FALSE() -> FALSE | I100: =FALSE() -> FALSE | K100: SANTAMARIA FRANCISCO | L100: 02-07-205-099 | M100: 0207205099 | N100: 6692 | O100: 61553 | P100: 40 - Residential Improvements | Q100: 94000 | R100: 35072 | W100: N | X100: Y | Y100: 1316 COURT O | Z100: HANOVER PARK | AA100: 0 | AB100: 5931.68 | AC100: 6342.07 | AD100: =FALSE() -> FALSE
...

Sheet Commercial
A1: Ok to Buy | B1: Do Not Buy | C1: TempBid | D1: Bid | E1: Comment | F1: 2024Comment | G1: 2024Bid | H1: 2023OkToBuy | I1: 2023DoNotBuy | J1: 2023Comment | K1: Taxpayer Name | L1: Parcel Number | M1: PINNoDashes | N1: Assessed Land | O1: Assessed Bldg | P1: ClassCode | Q1: SaleAmt | R1: SaleDt | S1: MortAmt | T1: MortDt | U1: 2ndMort | V1: 2ndMortDt | W1: Lien | X1: Judgmt | Y1: Property Address 1 | Z1: Property City | AA1: Back Tax | AB1: TotalTaxBilled | AC1: Judgment Amount | AD1: HalfInstallment
A2: =TRUE() -> TRUE | B2: =FALSE() -> FALSE | C2: 4 | D2: 4 | F2: strip center | G2: 4 | H2: =FALSE() -> FALSE | I2: =FALSE() -> FALSE | K2: MILLION WAYS SERIES LLC | L2: 02-02-317-002 | M2: 0202317002 | N2: 291035 | O2: 763001 | P2: 60 - Commercial Improvements | Q2: 3000000 | R2: 43662 | W2: N | X2: N | Y2: 610 E IRVING PARK RD | Z2: ROSELLE | AA2: 0 | AB2: 67316.02 | AC2: 71869.85 | AD2: =FALSE() -> FALSE
A3: =TRUE() -> TRUE | B3: =FALSE() -> FALSE | C3: 3 | D3: 3 | G3: 3 | H3: =TRUE() -> TRUE | I3: =FALSE() -> FALSE | K3: MANGY DAWG ROSELLE INC | L3: 02-03-213-002 | M3: 0203213002 | N3: 17540 | O3: 229865 | P3: 60 - Commercial Improvements | Q3: 625000 | R3: 43894 | W3: Y | X3: N | Y3: 101-03 E IRVING PARK RD | Z3: ROSELLE | AA3: 0 | AB3: 18591.76 | AC3: 9724.19 | AD3: =TRUE() -> TRUE
A4: =TRUE() -> TRUE | B4: =FALSE() -> FALSE | C4: 5 | D4: 5 | E4: hotel | H4: =TRUE() -> TRUE | I4: =FALSE() -> FALSE | K4: IHP HOSPITALITY LLC | L4: 03-05-200-031 | M4: 0305200031 | N4: 882130 | O4: 1968140 | P4: 60 - Commercial Improvements | Q4: 7375000 | R4: 44755 | S4: 3923700 | T4: 44755 | U4: 2419000 | V4: 44820 | W4: Y | X4: N | Y4: 1150 N ARLINGTON HTS | Z4: ITASCA | AA4: 0 | AB4: 206433.66 | AC4: 220377.93 | AD4: =FALSE() -> FALSE
A5: =TRUE() -> TRUE | B5: =FALSE() -> FALSE | C5: 3 | D5: 3 | H5: =TRUE() -> TRUE | I5: =FALSE() -> FALSE | K5: EDWINBERRY PROPERTIES LLC | L5: 05-09-107-004 | M5: 0509107004 | N5: 49866 | O5: 129162 | P5: 60 - Commercial Improvements | Q5: 490000 | R5: 44140 | S5: 450000 | T5: 44140 | U5: 208000 | V5: 44144 | W5: N | X5: N | Y5: 1600 N MAIN ST | Z5: WHEATON | AA5: 0 | AB5: 11538.72 | AC5: 12327.58 | AD5: =FALSE() -> FALSE
A6: =TRUE() -> TRUE | B6: =FALSE() -> FALSE | C6: 3 | D6: 3 | F6: apts | G6: 4 | H6: =FALSE() -> FALSE | I6: =FALSE() -> FALSE | K6: MILLION WAYS SERIES LLC | L6: 06-08-100-009 | M6: 0608100009 | N6: 35427 | O6: 362312 | P6: 60 - Commercial Improvements | R6: 43157 | S6: 2000000 | T6: 44230 | W6: Y | X6: Y | Y6: 9 N MAIN ST | Z6: LOMBARD | AA6: 0 | AB6: 30902.32 | AC6: 32998.22 | AD6: =FALSE() -> FALSE
A7: =TRUE() -> TRUE | B7: =FALSE() -> FALSE | C7: 3 | D7: 3 | F7: brewing company - store | G7: 3 | H7: =FALSE() -> FALSE | I7: =FALSE() -> FALSE | K7: TRIARC DEVELOPMENT LLC | L7: 06-08-105-013 | M7: 0608105013 | N7: 68139 | O7: 70410 | P7: 60 - Commercial Improvements | Q7: 470000 | R7: 38995 | W7: Y | X7: N | Y7: 218 E ST CHARLES RD | Z7: LOMBARD | AA7: 0 | AB7: 10764.56 | AC7: 5634.48 | AD7: =TRUE() -> TRUE
A8: =TRUE() -> TRUE | B8: =FALSE() -> FALSE | C8: 3 | D8: 3 | H8: =TRUE() -> TRUE | I8: =FALSE() -> FALSE | K8: CONSOLIDATED MANAGEMENT | L8: 06-08-121-020 | M8: 0608121020 | N8: 97423 | O8: 147698 | P8: 60 - Commercial Improvements | W8: N | X8: N | Y8: 15 E MAPLE ST | Z8: LOMBARD | AA8: 0 | AB8: 19044.68 | AC8: 20340.2 | AD8: =FALSE() -> FALSE
A9: =TRUE() -> TRUE | B9: =FALSE() -> FALSE | C9: 3 | D9: 3 | F9: fitness center | G9: 3 | H9: =FALSE() -> FALSE | I9: =TRUE() -> TRUE | K9: TRIARC DEVELOPMENT LLC | L9: 06-08-133-004 | M9: 0608133004 | N9: 28679 | O9: 99359 | P9: 60 - Commercial Improvements | Q9: 550000 | R9: 39437 | W9: N | X9: N | Y9: 216 E ST CHARLES RD | Z9: LOMBARD | AA9: 0 | AB9: 9947.92 | AC9: 5207.79 | AD9: =TRUE() -> TRUE
A10: =TRUE() -> TRUE | B10: =FALSE() -> FALSE | C10: 3 | D10: 3 | F10: dowtntown store | G10: 3 | H10: =FALSE() -> FALSE | I10: =FALSE() -> FALSE | K10: SIFLEET STACY | L10: 06-10-118-001 | M10: 0610118001 | N10: 11063 | O10: 106691 | P10: 60 - Commercial Improvements | Q10: 200000 | R10: 42647 | S10: 149500 | T10: 42647 | W10: Y | X10: N | Y10: 1 E PARK BLVD | Z10: VILLA PARK | AA10: 0 | AB10: 8899.98 | AC10: 9510.73 | AD10: =FALSE() -> FALSE
A11: =TRUE() -> TRUE | B11: =FALSE() -> FALSE | C11: 4 | D11: 4 | F11: office | G11: 3 | H11: =FALSE() -> FALSE | I11: =FALSE() -> FALSE | K11: DM EQUITIES LLC | L11: 06-19-305-006 | M11: 0619305006 | N11: 253469 | O11: 577359 | P11: 60 - Commercial Improvements | Q11: 2530000 | R11: 43413 | S11: 2640000 | T11: 43413 | W11: Y | X11: N | Y11: 555 WATERS EDGE | Z11: LOMBARD | AA11: 0 | AB11: 65128.62 | AC11: 69534.8 | AD11: =FALSE() -> FALSE
A12: =TRUE() -> TRUE | B12: =FALSE() -> FALSE | C12: 3 | D12: 3 | F12: dr office suite | G12: 4 | H12: =FALSE() -> FALSE | I12: =FALSE() -> FALSE | K12: SPK HOLDINGS LLC | L12: 06-21-405-020 | M12: 0621405020 | N12: 7819 | O12: 70367 | P12: 60 - Commercial Improvements | Q12: 235000 | R12: 42284 | W12: Y | X12: N | Y12: 1 TRANSAM PLAZA # 310 | Z12: OAKBROOK TERR | AA12: 0 | AB12: 6047.92 | AC12: 3170.04 | AD12: =TRUE() -> TRUE
A13: =TRUE() -> TRUE | B13: =FALSE() -> FALSE | C13: 3 | D13: 3 | F13: cannabis store | G13: 4 | H13: =FALSE() -> FALSE | I13: =FALSE() -> FALSE | K13: SUMMIT OBT LLC | L13: 06-22-100-008 | M13: 0622100008 | N13: 214085 | O13: 227137 | P13: 60 - Commercial Improvements | Q13: 1670000 | R13: 44958 | W13: Y | X13: N | Y13: 1S130 SUMMIT AVE | Z13: OAKBROOK TERR | AA13: 0 | AB13: 26176.36 | AC13: 27953.27 | AD13: =FALSE() -> FALSE
A14: =TRUE() -> TRUE | B14: =FALSE() -> FALSE | C14: 4 | D14: 4 | F14: office 1/2 installment | G14: 3 | H14: =FALSE() -> FALSE | I14: =FALSE() -> FALSE | K14: 1430 BRANDING DG LLC | L14: 06-30-407-009 | M14: 0630407009 | N14: 788470 | O14: 899680 | P14: 60 - Commercial Improvements | Q14: 3045000 | R14: 42551 | W14: Y | X14: Y | Y14: 1430 BRANDING AVE | Z14: DOWNERS GROVE | AA14: 0 | AB14: 96783.34 | AC14: 50579.3 | AD14: =TRUE() -> TRUE
A15: =TRUE() -> TRUE | B15: =FALSE() -> FALSE | C15: 3 | D15: 3 | F15: panera | G15: 3 | H15: =FALSE() -> FALSE | I15: =FALSE() -> FALSE | K15: PANERA LLC | L15: 07-10-105-013 | M15: 0710105013 | N15: 208880 | O15: 219486 | P15: 60 - Commercial Improvements | Q15: 2783000 | R15: 43474 | W15: N | X15: N | Y15: 1620 N ROUTE 59 | Z15: NAPERVILLE | AA15: 0 | AB15: 26738.18 | AC15: 28553.01 | AD15: =FALSE() -> FALSE
A16: =TRUE() -> TRUE | B16: =FALSE() -> FALSE | C16: 5 | D16: 5 | F16: offfice buildings | G16: 3 | H16: =FALSE() -> FALSE | I16: =FALSE() -> FALSE | K16: BOBR GROUP LLC | L16: 07-12-204-005 | M16: 0712204005 | N16: 628310 | O16: 1724338 | P16: 60 - Commercial Improvements | Q16: 10600000 | R16: 43636 | S16: 12000000 | T16: 43636 | W16: Y | X16: Y | Y16: 1717 PARK ST | Z16: NAPERVILLE | AA16: 0 | AB16: 144283.2 | AC16: 154032.31 | AD16: =FALSE() -> FALSE
A17: =TRUE() -> TRUE | B17: =FALSE() -> FALSE | C17: 3 | D17: 3 | F17: restaurant | G17: 4 | H17: =FALSE() -> FALSE | I17: =TRUE() -> TRUE | K17: 48 WEST CHICAGO LLC | L17: 07-13-436-016 | M17: 0713436016 | N17: 52963 | O17: 370507 | P17: 60 - Commercial Improvements | Q17: 1300000 | R17: 41669 | S17: 2975000 | T17: 42248 | U17: 1512000 | V17: 43224 | W17: Y | X17: Y | Y17: 36-50 W CHICAGO AVE | Z17: NAPERVILLE | AA17: 0 | AB17: 31547.26 | AC17: 33686.7 | AD17: =FALSE() -> FALSE
A18: =TRUE() -> TRUE | B18: =FALSE() -> FALSE | C18: 3 | D18: 3 | F18: white castle | G18: 4 | H18: =FALSE() -> FALSE | I18: =TRUE() -> TRUE | K18: HD WHITE CASTLE LLC | L18: 07-21-200-061 | M18: 0721200061 | N18: 123409 | O18: 141394 | P18: 60 - Commercial Improvements | Q18: 608500 | R18: 44862 | W18: Y | X18: N | Y18: 444 N RT 59 | Z18: AURORA | AA18: 0 | AB18: 20134.04 | AC18: 21503.09 | AD18: =FALSE() -> FALSE
A19: =TRUE() -> TRUE | B19: =FALSE() -> FALSE | C19: 3 | D19: 3 | H19: =TRUE() -> TRUE | I19: =FALSE() -> FALSE | K19: TF PORTFOLIO I LLC | L19: 09-04-403-001 | M19: 0904403001 | N19: 269890 | O19: 416180 | P19: 60 - Commercial Improvements | Q19: 2973333.3 | R19: 44893 | S19: 20000000 | T19: 44893 | W19: N | X19: N | Y19: 19-31 W OGDEN AVE | Z19: WESTMONT | AA19: 0 | AB19: 44589.76 | AC19: 47609.57 | AD19: =FALSE() -> FALSE
A20: =TRUE() -> TRUE | B20: =FALSE() -> FALSE | C20: 3 | D20: 3 | F20: office | G20: 4 | H20: =FALSE() -> FALSE | I20: =FALSE() -> FALSE | K20: WEST SUBURBAN BANK | L20: 09-08-116-007 | M20: 0908116007 | N20: 90733 | O20: 65758 | P20: 60 - Commercial Improvements | Q20: 300000 | R20: 43475 | S20: 412000 | T20: 43476 | W20: N | X20: N | Y20: 4925 FOREST AVE | Z20: DOWNERS GROVE | AA20: 0 | AB20: 10035.14 | AC20: 10722.51 | AD20: =FALSE() -> FALSE
A21: =TRUE() -> TRUE | B21: =FALSE() -> FALSE | C21: 3 | D21: 3 | H21: =TRUE() -> TRUE | I21: =FALSE() -> FALSE | K21: 6010 MANAGEMENT LLC | L21: 09-16-402-018 | M21: 0916402018 | N21: 200730 | O21: 163570 | P21: 60 - Commercial Improvements | Q21: 1200040 | R21: 45007 | W21: Y | X21: Y | Y21: 6010 S CASS AVE | Z21: WESTMONT | AA21: 0 | AB21: 24518.86 | AC21: 26183.88 | AD21: =FALSE() -> FALSE
A22: =TRUE() -> TRUE | B22: =FALSE() -> FALSE | C22: 3 | D22: 3 | F22: office suite | G22: 4 | H22: =FALSE() -> FALSE | I22: =FALSE() -> FALSE | K22: 6424 CASS PROPERTIES LLC | L22: 09-21-217-015 | M22: 0921217015 | N22: 22224 | O22: 41173 | P22: 60 - Commercial Improvements | Q22: 185000 | R22: 45105 | W22: Y | X22: N | Y22: 6424 S CASS AVE # 403 | Z22: WESTMONT | AA22: 0 | AB22: 4266.86 | AC22: 4564.87 | AD22: =FALSE() -> FALSE
A23: =TRUE() -> TRUE | B23: =FALSE() -> FALSE | C23: 5 | D23: 5 | F23: Hotel | G23: 5 | H23: =FALSE() -> FALSE | I23: =FALSE() -> FALSE | K23: A1 HOSPITALITY | L23: 09-26-402-028 | M23: 0926402028 | N23: 801980 | O23: 2622060 | P23: 60 - Commercial Improvements | Q23: 4080000 | R23: 41558 | S23: 8250000 | T23: 42738 | U23: 1270000 | V23: 43770 | W23: Y | X23: Y | Y23: 7800 KINGERY HWY | Z23: WILLOWBROOK | AA23: 0 | AB23: 163857.44 | AC23: 174927.81 | AD23: =FALSE() -> FALSE
A24: =TRUE() -> TRUE | B24: =FALSE() -> FALSE | C24: 3 | D24: 3 | H24: =TRUE() -> TRUE | I24: =FALSE() -> FALSE | K24: 1222 WEST ARGYLE LLC | L24: 09-30-401-130 | M24: 0930401130 | N24: 144503 | O24: 203255 | P24: 60 - Commercial Improvements | Y24: 7508 LEMONT RD | Z24: WOODRIDGE | AA24: 0 | AB24: 23103.68 | AC24: 12081.67 | AD24: =TRUE() -> TRUE
AB26: Total | AC26: =SUM(AC2:AC24) -> 1053093.8

Sheet Removed - Full Inst Under 3K
A1: Ok to Buy | B1: Do Not Buy | C1: TempBid | D1: Bid | E1: Comment | F1: 2024Comment | G1: 2024Bid | H1: 2023OkToBuy | I1: 2023DoNotBuy | J1: 2023Comment | K1: Taxpayer Name | L1: Parcel Number | M1: PINNoDashes | N1: Assessed Land | O1: Assessed Bldg | P1: ClassCode | Q1: SaleAmt | R1: SaleDt | S1: MortAmt | T1: MortDt | U1: 2ndMort | V1: 2ndMortDt | W1: Lien | X1: Judgmt | Y1: Property Address 1 | Z1: Property City | AA1: Back Tax | AB1: TotalTaxBilled | AC1: Judgment Amount | AD1: HalfInstallment
A2: =TRUE() -> TRUE | B2: =FALSE() -> FALSE | C2: 3 | H2: =FALSE() -> FALSE | I2: =FALSE() -> FALSE | K2: ESQUIVEL ALEJANDRO GUZMAN | L2: 01-03-304-022 | M2: 0103304022 | N2: 33518 | O2: 81804 | P2: 40 - Residential Improvements | Q2: 346000 | R2: 45322 | S2: 356500 | T2: 45600 | W2: N | X2: N | Y2: 914 BRYN MAWR AVE | Z2: BARTLETT | AA2: 0 | AB2: 142.96 | AC2: 162.61 | AD2: =FALSE() -> FALSE
A3: =TRUE() -> TRUE | B3: =FALSE() -> FALSE | C3: 2 | H3: =FALSE() -> FALSE | I3: =FALSE() -> FALSE | K3: MAYNARD DAVID | L3: 02-03-323-003 | M3: 0203323003 | N3: 6780 | O3: 31362 | P3: 40 - Residential Improvements | R3: 40214 | W3: N | X3: Y | Y3: 77 W CENTRAL AVE # 105 | Z3: ROSELLE | AA3: 0 | AB3: 2265.08 | AC3: 2427.97 | AD3: =FALSE() -> FALSE
A4: =TRUE() -> TRUE | B4: =FALSE() -> FALSE | C4: 2 | H4: =FALSE() -> FALSE | I4: =FALSE() -> FALSE | K4: KEAR DANIEL & FELICIDAD | L4: 02-22-112-081 | M4: 0222112081 | N4: 5369 | O4: 36031 | P4: 40 - Residential Improvements | Q4: 130000 | R4: 45526 | W4: N | X4: N | Y4: 152 W DUNTEMAN DR # 201 | Z4: GLENDALE HTS | AA4: 0 | AB4: 2339.48 | AC4: 2507.4 | AD4: =FALSE() -> FALSE
A5: =TRUE() -> TRUE | B5: =FALSE() -> FALSE | C5: 2 | H5: =FALSE() -> FALSE | I5: =FALSE() -> FALSE | K5: SANDERS LOIS P | L5: 02-22-113-100 | M5: 0222113100 | N5: 5369 | O5: 39104 | P5: 40 - Residential Improvements | Q5: 129000 | R5: 38162 | W5: N | X5: N | Y5: 200 S WATERS EDGE DR # 202 | Z5: GLENDALE HTS | AA5: 0 | AB5: 2622.52 | AC5: 2809.54 | AD5: =FALSE() -> FALSE
A6: =TRUE() -> TRUE | B6: =FALSE() -> FALSE | C6: 2 | H6: =FALSE() -> FALSE | I6: =FALSE() -> FALSE | K6: ST ANDREW UKRAINIAN CHURCH | L6: 02-23-418-004 | M6: 0223418004 | N6: 5861 | O6: 26299 | P6: 40 - Residential Improvements | R6: 36985 | W6: N | X6: N | Y6: 300 E ARMY TRAIL RD # 15 | Z6: BLOOMINGDALE | AA6: 0 | AB6: 2168.7 | AC6: 2325.09 | AD6: =FALSE() -> FALSE
A7: =TRUE() -> TRUE | B7: =FALSE() -> FALSE | C7: 2 | H7: =FALSE() -> FALSE | I7: =FALSE() -> FALSE | K7: ST ANDREW UKRANIAN CHURCH | L7: 02-23-418-008 | M7: 0223418008 | N7: 5861 | O7: 29021 | P7: 40 - Residential Improvements | R7: 36985 | W7: N | X7: N | Y7: 300 E ARMY TRAIL RD # 19 | Z7: BLOOMINGDALE | AA7: 0 | AB7: 2413.04 | AC7: 2585.92 | AD7: =FALSE() -> FALSE
A8: =TRUE() -> TRUE | B8: =FALSE() -> FALSE | C8: 3 | H8: =FALSE() -> FALSE | I8: =FALSE() -> FALSE | K8: AIARDO L & R KIRBY | L8: 02-24-207-008 | M8: 0224207008 | N8: 5500 | O8: 35134 | P8: 40 - Residential Improvements | Q8: 21000 | R8: 41002 | S8: 6000 | T8: 41002 | W8: N | X8: Y | Y8: 941 N RT 53 # 101C | Z8: ADDISON | AA8: 0 | AB8: 1727.18 | AC8: 1853.76 | AD8: =FALSE() -> FALSE
A9: =TRUE() -> TRUE | B9: =FALSE() -> FALSE | C9: 3 | H9: =FALSE() -> FALSE | I9: =FALSE() -> FALSE | K9: ABBAS NAJAM & SYEDA KAZMI | L9: 02-29-111-090 | M9: 0229111090 | N9: 9492 | O9: 28475 | P9: 40 - Residential Improvements | Q9: 186000 | R9: 45768 | S9: 139500 | T9: 45768 | W9: N | X9: N | Y9: 105 W ELK TRL # 305 | Z9: CAROL STREAM | AA9: 0 | AB9: 2570.88 | AC9: 2754.41 | AD9: =FALSE() -> FALSE
A10: =TRUE() -> TRUE | B10: =FALSE() -> FALSE | C10: 3 | H10: =FALSE() -> FALSE | I10: =FALSE() -> FALSE | K10: PATEL ARPAN | L10: 02-29-111-123 | M10: 0229111123 | N10: 9492 | O10: 13249 | P10: 40 - Residential Improvements | Q10: 172000 | R10: 45754 | S10: 154800 | T10: 45754 | W10: N | X10: N | Y10: 161 ELK TRL # 262 | Z10: CAROL STREAM | AA10: 0 | AB10: 1264.64 | AC10: 1360 | AD10: =FALSE() -> FALSE
A11: =TRUE() -> TRUE | B11: =FALSE() -> FALSE | C11: 3 | H11: =FALSE() -> FALSE | I11: =FALSE() -> FALSE | K11: THOMAS III JOHN | L11: 02-29-117-009 | M11: 0229117009 | N11: 8562 | O11: 34467 | P11: 40 - Residential Improvements | Q11: 181000 | R11: 45414 | S11: 183750 | T11: 45700 | W11: N | X11: N | Y11: 122 KLEIN CREEK CT # 3C | Z11: CAROL STREAM | AA11: 0 | AB11: 534.04 | AC11: 580.09 | AD11: =FALSE() -> FALSE
A12: =TRUE() -> TRUE | B12: =FALSE() -> FALSE | C12: 3 | H12: =FALSE() -> FALSE | I12: =FALSE() -> FALSE | K12: GNATOVYCH VOLODYMYR | L12: 02-33-204-172 | M12: 0233204172 | N12: 12105 | O12: 26000 | P12: 40 - Residential Improvements | Q12: 335000 | R12: 45562 | S12: 288000 | T12: 45562 | W12: N | X12: N | Y12: 1419 CLUB DR # A | Z12: GLENDALE HTS | AA12: 0 | AB12: 2022.42 | AC12: 2168.93 | AD12: =FALSE() -> FALSE
A13: =TRUE() -> TRUE | B13: =FALSE() -> FALSE | C13: 2 | H13: =FALSE() -> FALSE | I13: =FALSE() -> FALSE | K13: LUKASIK MITCHELL & D H | L13: 03-20-412-010 | M13: 0320412010 | N13: 41141 | O13: 59383 | P13: 40 - Residential Improvements | W13: N | X13: N | Y13: 701 CRAIG PL | Z13: ADDISON | AA13: 0 | AB13: 1700.7 | AC13: 1825.5 | AD13: =FALSE() -> FALSE
A14: =TRUE() -> TRUE | B14: =FALSE() -> FALSE | C14: 2 | G14: 2 | H14: =FALSE() -> FALSE | I14: =FALSE() -> FALSE | K14: RUFFIN TERRY K | L14: 03-24-314-006 | M14: 0324314006 | N14: 5265 | O14: 33602 | P14: 40 - Residential Improvements | Q14: 85000 | R14: 44482 | W14: N | X14: Y | Y14: 310 GEORGE ST # 2SE | Z14: BENSENVILLE | AA14: 0 | AB14: 2683.82 | AC14: 2874.98 | AD14: =FALSE() -> FALSE
A15: =TRUE() -> TRUE | B15: =FALSE() -> FALSE | C15: 2 | H15: =FALSE() -> FALSE | I15: =FALSE() -> FALSE | K15: VILLASENOR MIGUEL ANGEL | L15: 03-25-120-036 | M15: 0325120036 | N15: 5994 | O15: 23953 | P15: 40 - Residential Improvements | Q15: 139000 | R15: 45768 | W15: N | X15: N | Y15: 1043 S YORK RD # 412 | Z15: BENSENVILLE | AA15: 0 | AB15: 2183.92 | AC15: 2341.34 | AD15: =FALSE() -> FALSE
A16: =TRUE() -> TRUE | B16: =FALSE() -> FALSE | C16: 3 | G16: 2 | H16: =TRUE() -> TRUE | I16: =FALSE() -> FALSE | K16: MANCZKO THADDEUS J | L16: 03-28-315-008 | M16: 0328315008 | N16: 43240 | O16: 64844 | P16: 40 - Residential Improvements | R16: 34655 | S16: 275000 | T16: 38579 | W16: N | X16: Y | Y16: 239 S HALE ST | Z16: ADDISON | AA16: 0 | AB16: 2853.78 | AC16: 2992.2 | AD16: =FALSE() -> FALSE
A17: =TRUE() -> TRUE | B17: =FALSE() -> FALSE | C17: 2 | H17: =FALSE() -> FALSE | I17: =FALSE() -> FALSE | K17: MERKO GRISELDA | L17: 03-28-318-056 | M17: 0328318056 | N17: 3209 | O17: 28914 | P17: 40 - Residential Improvements | Q17: 101000 | R17: 45559 | W17: N | X17: N | Y17: 300 W FULLERTON AVE # 227 | Z17: ADDISON | AA17: 0 | AB17: 2264.08 | AC17: 2426.9 | AD17: =FALSE() -> FALSE
A18: =TRUE() -> TRUE | B18: =FALSE() -> FALSE | C18: 2 | H18: =FALSE() -> FALSE | I18: =FALSE() -> FALSE | K18: ESTATE ASSET GROUP LLC | L18: 03-28-400-014 | M18: 0328400014 | N18: 42250 | O18: 43294 | P18: 40 - Residential Improvements | Q18: 116000 | R18: 45686 | W18: N | X18: N | Y18: 8 S IOWA AVE | Z18: ADDISON | AA18: 0 | AB18: 1966.42 | AC18: 2109.15 | AD18: =FALSE() -> FALSE
A19: =TRUE() -> TRUE | B19: =FALSE() -> FALSE | C19: 2 | H19: =FALSE() -> FALSE | I19: =FALSE() -> FALSE | K19: GUDMUNDSON ERIC A | L19: 03-29-213-031 | M19: 0329213031 | N19: 4591 | O19: 42098 | P19: 40 - Residential Improvements | Q19: 91000 | R19: 37166 | W19: N | X19: N | Y19: 235 N MILL RD # 216B | Z19: ADDISON | AA19: 0 | AB19: 2726.84 | AC19: 2920.9 | AD19: =FALSE() -> FALSE
A20: =TRUE() -> TRUE | B20: =FALSE() -> FALSE | C20: 2 | H20: =TRUE() -> TRUE | I20: =FALSE() -> FALSE | K20: BARI SAQIB I | L20: 05-03-211-182 | M20: 0503211182 | N20: 3107 | O20: 29441 | P20: 40 - Residential Improvements | Q20: 131000 | R20: 45597 | W20: N | X20: N | Y20: 1129 CEDAR ST # 1B | Z20: GLENDALE HTS | AA20: 0 | AB20: 2724.52 | AC20: 2918.42 | AD20: =FALSE() -> FALSE
A21: =TRUE() -> TRUE | B21: =FALSE() -> FALSE | C21: 2 | H21: =FALSE() -> FALSE | I21: =FALSE() -> FALSE | K21: YAKOOB MUHAMMAD & AFIFAH | L21: 05-23-321-194 | M21: 0523321194 | N21: 5399 | O21: 34135 | P21: 40 - Residential Improvements | Q21: 155500 | R21: 45719 | W21: N | X21: Y | Y21: 461 RAINTREE CT # 1-D | Z21: GLEN ELLYN | AA21: 0 | AB21: 2332.16 | AC21: 2499.58 | AD21: =FALSE() -> FALSE
A22: =TRUE() -> TRUE | B22: =FALSE() -> FALSE | C22: 2 | H22: =FALSE() -> FALSE | I22: =FALSE() -> FALSE | K22: YOUNG TR ROSEMARY | L22: 05-27-106-095 | M22: 0527106095 | N22: 6920 | O22: 56438 | P22: 40 - Residential Improvements | W22: N | X22: N | Y22: 1661 VALLEY FORGE CT # D | Z22: WHEATON | AA22: 0 | AB22: 1231.68 | AC22: 1324.82 | AD22: =FALSE() -> FALSE
A23: =TRUE() -> TRUE | B23: =FALSE() -> FALSE | C23: 2 | H23: =FALSE() -> FALSE | I23: =FALSE() -> FALSE | K23: TUREK ROSE MARIE | L23: 06-02-322-059 | M23: 0602322059 | N23: 3287 | O23: 29533 | P23: 40 - Residential Improvements | Q23: 62000 | R23: 40690 | W23: N | X23: Y | Y23: 255 S WEST AVE | Z23: ELMHURST | AA23: 0 | AB23: 1013.66 | AC23: 1092.08 | AD23: =FALSE() -> FALSE
A24: =TRUE() -> TRUE | B24: =FALSE() -> FALSE | C24: 2 | H24: =FALSE() -> FALSE | I24: =FALSE() -> FALSE | K24: JONES JAMES D | L24: 06-02-322-065 | M24: 0602322065 | N24: 2585 | O24: 23174 | P24: 40 - Residential Improvements | Q24: 58000 | R24: 42200 | W24: N | X24: N | Y24: 255 S WEST AVE # 402 | Z24: ELMHURST | AA24: 0 | AB24: 1070.26 | AC24: 1152.5 | AD24: =FALSE() -> FALSE
A25: =TRUE() -> TRUE | B25: =FALSE() -> FALSE | C25: 2 | H25: =FALSE() -> FALSE | I25: =FALSE() -> FALSE | K25: NURAIN SABA & SUMERA FATIMA | L25: 06-04-418-007 | M25: 0604418007 | N25: 3536 | O25: 31761 | P25: 40 - Residential Improvements | Q25: 54000 | R25: 41900 | W25: Y | X25: N | Y25: 323 N PRINCETON AVE # 7 | Z25: VILLA PARK | AA25: 0 | AB25: 2667.8 | AC25: 2857.88 | AD25: =FALSE() -> FALSE
A26: =TRUE() -> TRUE | B26: =FALSE() -> FALSE | C26: 2 | H26: =FALSE() -> FALSE | I26: =FALSE() -> FALSE | K26: AUGUST RICHARD | L26: 06-19-203-054 | M26: 0619203054 | N26: 3006 | O26: 27067 | P26: 40 - Residential Improvements | R26: 43725 | W26: N | X26: Y | Y26: 1320A LORE LN # 106 | Z26: LOMBARD | AA26: 0 | AB26: 938.02 | AC26: 1011.34 | AD26: =FALSE() -> FALSE
A27: =TRUE() -> TRUE | B27: =FALSE() -> FALSE | C27: 3 | H27: =FALSE() -> FALSE | I27: =FALSE() -> FALSE | K27: SENS JACOB O | L27: 06-19-212-046 | M27: 0619212046 | N27: 3817 | O27: 34356 | P27: 40 - Residential Improvements | Q27: 130000 | R27: 45408 | S27: 104000 | T27: 45408 | W27: N | X27: N | Y27: 1301 S FINLEY RD # 306 | Z27: LOMBARD | AA27: 0 | AB27: 1722.74 | AC27: 1849.02 | AD27: =FALSE() -> FALSE
A28: =TRUE() -> TRUE | B28: =FALSE() -> FALSE | C28: 3 | G28: 2 | H28: =FALSE() -> FALSE | I28: =FALSE() -> FALSE | K28: BENNETT RUBY & SAMMUEL | L28: 06-19-212-079 | M28: 0619212079 | N28: 4672 | O28: 42045 | P28: 40 - Residential Improvements | Q28: 107000 | R28: 37292 | S28: 244500 | T28: 39346 | W28: N | X28: Y | Y28: 1301 S FINLEY RD # 417 | Z28: LOMBARD | AA28: 0 | AB28: 2386.58 | AC28: 2557.68 | AD28: =FALSE() -> FALSE
A29: =TRUE() -> TRUE | B29: =FALSE() -> FALSE | C29: 2 | H29: =FALSE() -> FALSE | I29: =FALSE() -> FALSE | K29: RIENDEAU CHRISTINE | L29: 06-19-213-010 | M29: 0619213010 | N29: 3817 | O29: 34356 | P29: 40 - Residential Improvements | Q29: 67000 | R29: 36497 | W29: N | X29: Y | Y29: 1311 S FINLEY RD # 110 | Z29: LOMBARD | AA29: 0 | AB29: 1499.5 | AC29: 1576.98 | AD29: =FALSE() -> FALSE
A30: =TRUE() -> TRUE | B30: =FALSE() -> FALSE | C30: 2 | H30: =FALSE() -> FALSE | I30: =FALSE() -> FALSE | K30: SYED SAJID | L30: 06-19-214-013 | M30: 0619214013 | N30: 4747 | O30: 42715 | P30: 40 - Residential Improvements | Q30: 180000 | R30: 45413 | W30: N | X30: N | Y30: 1321 S FINLEY RD # 113 | Z30: LOMBARD | AA30: 0 | AB30: 2444.46 | AC30: 2619.46 | AD30: =FALSE() -> FALSE
A31: =TRUE() -> TRUE | B31: =FALSE() -> FALSE | C31: 2 | H31: =FALSE() -> FALSE | I31: =FALSE() -> FALSE | K31: RISTINE MYRNA B | L31: 06-20-207-037 | M31: 0620207037 | N31: 4207 | O31: 38000 | P31: 40 - Residential Improvements | R31: 35759 | W31: Y | X31: Y | Y31: 1406 S FAIRFIELD AVE # 37A | Z31: LOMBARD | AA31: 0 | AB31: 2657.72 | AC31: 2847.12 | AD31: =FALSE() -> FALSE
A32: =TRUE() -> TRUE | B32: =FALSE() -> FALSE | C32: 3 | H32: =FALSE() -> FALSE | I32: =FALSE() -> FALSE | K32: ROSS KAREN J | L32: 06-21-211-039 | M32: 0621211039 | N32: 6240 | O32: 56211 | P32: 40 - Residential Improvements | S32: 35820 | T32: 38023 | W32: Y | X32: Y | Y32: 18W055 STANDISH LN | Z32: VILLA PARK | AA32: 0 | AB32: 340.08 | AC32: 373.03 | AD32: =FALSE() -> FALSE
A33: =TRUE() -> TRUE | B33: =FALSE() -> FALSE | C33: 2 | H33: =FALSE() -> FALSE | I33: =FALSE() -> FALSE | K33: SELBY LAURA G | L33: 06-21-211-081 | M33: 0621211081 | N33: 4250 | O33: 38217 | P33: 40 - Residential Improvements | R33: 37473 | W33: N | X33: N | Y33: 1S265 DILLON LN | Z33: VILLA PARK | AA33: 0 | AB33: 2548.1 | AC33: 2730.09 | AD33: =FALSE() -> FALSE
A34: =TRUE() -> TRUE | B34: =FALSE() -> FALSE | C34: 2 | H34: =TRUE() -> TRUE | I34: =FALSE() -> FALSE | K34: WET N BLUE INC | L34: 06-28-107-103 | M34: 0628107103 | N34: 4477 | O34: 40304 | P34: 40 - Residential Improvements | Q34: 128000 | R34: 44879 | W34: N | X34: Y | Y34: 40 N TOWER RD # 1-E | Z34: OAK BROOK | AA34: 0 | AB34: 2729.86 | AC34: 2924.12 | AD34: =FALSE() -> FALSE
A35: =TRUE() -> TRUE | B35: =FALSE() -> FALSE | C35: 3 | G35: 2 | H35: =FALSE() -> FALSE | I35: =FALSE() -> FALSE | K35: BREMER DAVID | L35: 06-28-107-206 | M35: 0628107206 | N35: 4801 | O35: 43202 | P35: 40 - Residential Improvements | Q35: 113500 | R35: 37706 | S35: 90000 | T35: 37785 | W35: N | X35: Y | Y35: 20 N TOWER RD # 10H | Z35: OAK BROOK | AA35: 0 | AB35: 2375.22 | AC35: 2545.54 | AD35: =FALSE() -> FALSE
A36: =TRUE() -> TRUE | B36: =FALSE() -> FALSE | C36: 2 | H36: =FALSE() -> FALSE | I36: =FALSE() -> FALSE | K36: DAWSON MICHAEL C | L36: 06-28-107-276 | M36: 0628107276 | N36: 4477 | O36: 40304 | P36: 40 - Residential Improvements | Q36: 74500 | R36: 35020 | W36: N | X36: Y | Y36: 20 N TOWER RD # 1-L-W | Z36: OAK BROOK | AA36: 0 | AB36: 2729.86 | AC36: 2924.12 | AD36: =FALSE() -> FALSE
A37: =TRUE() -> TRUE | B37: =FALSE() -> FALSE | C37: 2 | H37: =FALSE() -> FALSE | I37: =FALSE() -> FALSE | K37: PRATT MINA M | L37: 07-09-206-040 | M37: 0709206040 | N37: 46375 | O37: 56847 | P37: 40 - Residential Improvements | W37: N | X37: N | Y37: 30W162 CLAYMORE LN | Z37: NAPERVILLE | AA37: 0 | AB37: 1405.7 | AC37: 1510.59 | AD37: =FALSE() -> FALSE
A38: =TRUE() -> TRUE | B38: =FALSE() -> FALSE | C38: 2 | H38: =FALSE() -> FALSE | I38: =FALSE() -> FALSE | K38: TAGLIAPIETRA RONALD | L38: 07-12-426-011 | M38: 0712426011 | N38: 5787 | O38: 44783 | P38: 40 - Residential Improvements | Q38: 222000 | R38: 45496 | W38: N | X38: N | Y38: 520 BURNING TREE LN # 112 | Z38: NAPERVILLE | AA38: 0 | AB38: 2610.74 | AC38: 2796.96 | AD38: =FALSE() -> FALSE
A39: =TRUE() -> TRUE | B39: =FALSE() -> FALSE | C39: 2 | H39: =FALSE() -> FALSE | I39: =FALSE() -> FALSE | K39: CAMPBELL RAYMOND C | L39: 07-12-426-094 | M39: 0712426094 | N39: 4741 | O39: 36815 | P39: 40 - Residential Improvements | Q39: 60000 | R39: 41186 | W39: N | X39: N | Y39: 1041 N MILL ST # 103 | Z39: NAPERVILLE | AA39: 0 | AB39: 2057.94 | AC39: 2206.85 | AD39: =FALSE() -> FALSE
A40: =TRUE() -> TRUE | B40: =FALSE() -> FALSE | C40: 2 | H40: =FALSE() -> FALSE | I40: =FALSE() -> FALSE | K40: GARBACZ JACK | L40: 07-12-426-169 | M40: 0712426169 | N40: 4830 | O40: 36114 | P40: 40 - Residential Improvements | Q40: 96000 | R40: 37629 | W40: N | X40: N | Y40: 1060 MILL ST # 1-203 | Z40: NAPERVILLE | AA40: 0 | AB40: 1529.78 | AC40: 1643.04 | AD40: =FALSE() -> FALSE
A41: =TRUE() -> TRUE | B41: =FALSE() -> FALSE | C41: 2 | G41: 2 | H41: =TRUE() -> TRUE | I41: =FALSE() -> FALSE | K41: HUNT ANDRE | L41: 07-21-306-015 | M41: 0721306015 | N41: 3472 | O41: 27210 | P41: 40 - Residential Improvements | Q41: 78000 | R41: 39542 | W41: N | X41: Y | Y41: 285 N GREGORY ST # 2-3 | Z41: AURORA | AA41: 0 | AB41: 1724.6 | AC41: 1851.01 | AD41: =FALSE() -> FALSE
A42: =TRUE() -> TRUE | B42: =FALSE() -> FALSE | C42: 3 | H42: =TRUE() -> TRUE | I42: =FALSE() -> FALSE | K42: KALKI MANAGEMENT LLC | L42: 07-21-306-029 | M42: 0721306029 | N42: 3817 | O42: 30037 | P42: 40 - Residential Improvements | Q42: 71000 | R42: 42935 | S42: 450000 | T42: 45239 | W42: N | X42: N | Y42: 291 GREGORY ST # 17 | Z42: AURORA | AA42: 0 | AB42: 2574.06 | AC42: 2757.81 | AD42: =FALSE() -> FALSE
A43: =TRUE() -> TRUE | B43: =FALSE() -> FALSE | C43: 3 | H43: =TRUE() -> TRUE | I43: =FALSE() -> FALSE | K43: KALKI MANAGEMENT LLC | L43: 07-21-306-096 | M43: 0721306096 | N43: 3906 | O43: 30761 | P43: 40 - Residential Improvements | Q43: 74000 | R43: 42947 | S43: 450000 | T43: 45239 | W43: N | X43: N | Y43: 219 GREGORY ST # 12 | Z43: AURORA | AA43: 0 | AB43: 2635.86 | AC43: 2823.78 | AD43: =FALSE() -> FALSE
A44: =TRUE() -> TRUE | B44: =FALSE() -> FALSE | C44: 3 | H44: =TRUE() -> TRUE | I44: =FALSE() -> FALSE | K44: KALKI MANAGEMENT LLC | L44: 07-21-306-168 | M44: 0721306168 | N44: 3906 | O44: 30761 | P44: 40 - Residential Improvements | Q44: 207 | R44: 43027 | S44: 450000 | T44: 45239 | W44: N | X44: N | Y44: 177 GREGORY ST # 18 | Z44: AURORA | AA44: 0 | AB44: 2635.86 | AC44: 2823.78 | AD44: =FALSE() -> FALSE
A45: =TRUE() -> TRUE | B45: =FALSE() -> FALSE | C45: 3 | H45: =TRUE() -> TRUE | I45: =FALSE() -> FALSE | K45: KALKI MANAGEMENT LLC | L45: 07-21-306-199 | M45: 0721306199 | N45: 3906 | O45: 30761 | P45: 40 - Residential Improvements | Q45: 79000 | R45: 42935 | S45: 450000 | T45: 45239 | W45: N | X45: N | Y45: 141 GREGORY ST # 13 | Z45: AURORA | AA45: 0 | AB45: 2635.86 | AC45: 2823.78 | AD45: =FALSE() -> FALSE
A46: =TRUE() -> TRUE | B46: =FALSE() -> FALSE | C46: 2 | H46: =TRUE() -> TRUE | I46: =FALSE() -> FALSE | K46: CHOU JIMMY JINYO | L46: 08-01-414-036 | M46: 0801414036 | N46: 6629 | O46: 35621 | P46: 40 - Residential Improvements | Q46: 53000 | R46: 42781 | W46: N | X46: N | Y46: 4439 ARBOR CIR # 21 | Z46: DOWNERS GROVE | AA46: 0 | AB46: 1958.78 | AC46: 2101 | AD46: =FALSE() -> FALSE
A47: =TRUE() -> TRUE | B47: =FALSE() -> FALSE | C47: 2 | H47: =FALSE() -> FALSE | I47: =FALSE() -> FALSE | K47: WISCHOEFFER WILLIAM & LYNDA | L47: 08-02-318-156 | M47: 0802318156 | N47: 5709 | O47: 43532 | P47: 40 - Residential Improvements | Q47: 175000 | R47: 45660 | W47: N | X47: N | Y47: 4731 ST JOSEPH CREEK # 3-H | Z47: LISLE | AA47: 0 | AB47: 85.04 | AC47: 100.78 | AD47: =FALSE() -> FALSE
A48: =TRUE() -> TRUE | B48: =FALSE() -> FALSE | C48: 2 | G48: 2 | H48: =FALSE() -> FALSE | I48: =FALSE() -> FALSE | K48: WALKER KATHLEEN | L48: 08-04-412-236 | M48: 0804412236 | N48: 4668 | O48: 39149 | P48: 40 - Residential Improvements | Q48: 75000 | R48: 42423 | W48: N | X48: Y | Y48: 4518 BEAU MONDE DR # 105 | Z48: LISLE | AA48: 0 | AB48: 2481.34 | AC48: 2658.83 | AD48: =FALSE() -> FALSE
A49: =TRUE() -> TRUE | B49: =FALSE() -> FALSE | C49: 2 | H49: =FALSE() -> FALSE | I49: =FALSE() -> FALSE | K49: GLANTZ RICHARD M | L49: 08-11-211-099 | M49: 0811211099 | N49: 6136 | O49: 42798 | P49: 40 - Residential Improvements | Q49: 65000 | R49: 35376 | W49: N | X49: N | Y49: 420 WALNUT CREEK # 3203 | Z49: LISLE | AA49: 0 | AB49: 2393.86 | AC49: 2565.44 | AD49: =FALSE() -> FALSE
A50: =TRUE() -> TRUE | B50: =FALSE() -> FALSE | C50: 2 | H50: =FALSE() -> FALSE | I50: =FALSE() -> FALSE | K50: SLEIKUS ALGIRDAS | L50: 08-11-412-008 | M50: 0811412008 | N50: 5939 | O50: 36618 | P50: 40 - Residential Improvements | Q50: 88000 | R50: 42885 | W50: N | X50: N | Y50: 5540 WALNUT AVE # 8A | Z50: DOWNERS GROVE | AA50: 0 | AB50: 1724.22 | AC50: 1850.6 | AD50: =FALSE() -> FALSE
A51: =TRUE() -> TRUE | B51: =FALSE() -> FALSE | C51: 2 | H51: =FALSE() -> FALSE | I51: =FALSE() -> FALSE | K51: FREDENDALL KATHLEEN | L51: 08-11-416-053 | M51: 0811416053 | N51: 4953 | O51: 30197 | P51: 40 - Residential Improvements | Q51: 60000 | R51: 42279 | W51: N | X51: Y | Y51: 5400 S WALNUT AVE # 409 | Z51: DOWNERS GROVE | AA51: 0 | AB51: 1762.74 | AC51: 1891.72 | AD51: =FALSE() -> FALSE
A52: =TRUE() -> TRUE | B52: =FALSE() -> FALSE | C52: 2 | H52: =TRUE() -> TRUE | I52: =FALSE() -> FALSE | K52: PLOCINSKI EDWARD | L52: 08-15-105-451 | M52: 0815105451 | N52: 7670 | O52: 34219 | P52: 40 - Residential Improvements | Q52: 125000 | R52: 44411 | W52: N | X52: N | Y52: 5700 HILLCREST LN # 1H | Z52: LISLE | AA52: 0 | AB52: 2665.76 | AC52: 2855.7 | AD52: =FALSE() -> FALSE
A53: =TRUE() -> TRUE | B53: =FALSE() -> FALSE | C53: 2 | H53: =TRUE() -> TRUE | I53: =FALSE() -> FALSE | K53: KIRCHER THOMAS M | L53: 08-25-414-014 | M53: 0825414014 | N53: 9719 | O53: 30176 | P53: 40 - Residential Improvements | Q53: 40000 | R53: 41514 | W53: N | X53: Y | Y53: 2218 COUNTRY CLUB DR # 33-14C | Z53: WOODRIDGE | AA53: 0 | AB53: 2598.08 | AC53: 2783.45 | AD53: =FALSE() -> FALSE
A54: =TRUE() -> TRUE | B54: =FALSE() -> FALSE | C54: 2 | H54: =TRUE() -> TRUE | I54: =FALSE() -> FALSE | K54: GAINES MICHELLE A | L54: 08-25-422-048 | M54: 0825422048 | N54: 9555 | O54: 21739 | P54: 40 - Residential Improvements | Q54: 30000 | R54: 41864 | W54: N | X54: Y | Y54: 2037 COUNTRY CLUB DR # 16B | Z54: WOODRIDGE | AA54: 0 | AB54: 1734.56 | AC54: 1861.65 | AD54: =FALSE() -> FALSE
A55: =TRUE() -> TRUE | B55: =FALSE() -> FALSE | C55: 2 | G55: 3 | H55: =FALSE() -> FALSE | I55: =FALSE() -> FALSE | K55: KUBA MARK C | L55: 08-32-110-201 | M55: 0832110201 | N55: 3539 | O55: 31096 | P55: 40 - Residential Improvements | Q55: 49000 | R55: 34912 | W55: N | X55: N | Y55: 228 BAILEY RD # F | Z55: NAPERVILLE | AA55: 0 | AB55: 1631.68 | AC55: 1751.82 | AD55: =FALSE() -> FALSE
A56: =TRUE() -> TRUE | B56: =FALSE() -> FALSE | C56: 2 | H56: =FALSE() -> FALSE | I56: =FALSE() -> FALSE | K56: BETTINI JOSEPH A | L56: 08-32-110-234 | M56: 0832110234 | N56: 4317 | O56: 37977 | P56: 40 - Residential Improvements | W56: Y | X56: Y | Y56: 244 E BAILEY RD # 244-D | Z56: NAPERVILLE | AA56: 0 | AB56: 2100.86 | AC56: 2252.67 | AD56: =FALSE() -> FALSE
A57: =TRUE() -> TRUE | B57: =FALSE() -> FALSE | C57: 2 | H57: =FALSE() -> FALSE | I57: =FALSE() -> FALSE | K57: HOCK LAURIE A & KARON A | L57: 08-36-109-116 | M57: 0836109116 | N57: 3550 | O57: 30745 | P57: 40 - Residential Improvements | W57: N | X57: Y | Y57: 2429 SPRING ST # 4302 | Z57: WOODRIDGE | AA57: 0 | AB57: 2141.92 | AC57: 2296.5 | AD57: =FALSE() -> FALSE
A58: =TRUE() -> TRUE | B58: =FALSE() -> FALSE | C58: 2 | G58: 2 | H58: =TRUE() -> TRUE | I58: =FALSE() -> FALSE | K58: GOUNTANIS JOHN | L58: 09-05-122-081 | M58: 0905122081 | N58: 11868 | O58: 39639 | P58: 40 - Residential Improvements | Q58: 52500 | R58: 40961 | W58: N | X58: Y | Y58: 4225 SARATOGA AVE # 303-B | Z58: DOWNERS GROVE | AA58: 0 | AB58: 2032.82 | AC58: 2180.04 | AD58: =FALSE() -> FALSE
A59: =TRUE() -> TRUE | B59: =FALSE() -> FALSE | C59: 2 | G59: 2 | H59: =FALSE() -> FALSE | I59: =FALSE() -> FALSE | K59: CLAVER DANIEL | L59: 09-08-420-108 | M59: 0908420108 | N59: 9942 | O59: 29773 | P59: 40 - Residential Improvements | Q59: 117500 | R59: 38349 | W59: N | X59: Y | Y59: 5125 BLODGETT AVE # 319T | Z59: DOWNERS GROVE | AA59: 0 | AB59: 2273.74 | AC59: 2437.22 | AD59: =FALSE() -> FALSE
A60: =TRUE() -> TRUE | B60: =FALSE() -> FALSE | C60: 2 | H60: =FALSE() -> FALSE | I60: =FALSE() -> FALSE | K60: ARBACIAUSKAS M | L60: 09-14-122-129 | M60: 0914122129 | N60: 9486 | O60: 32645 | P60: 40 - Residential Improvements | Q60: 52000 | R60: 40458 | W60: N | X60: Y | Y60: 531 CARLYSLE DR # 3 | Z60: CLARENDON HILLS | AA60: 0 | AB60: 2655.1 | AC60: 2844.32 | AD60: =FALSE() -> FALSE
A61: =TRUE() -> TRUE | B61: =FALSE() -> FALSE | C61: 2 | H61: =FALSE() -> FALSE | I61: =FALSE() -> FALSE | K61: DOCTOR YE LLC | L61: 09-14-303-300 | M61: 0914303300 | N61: 8626 | O61: 31307 | P61: 40 - Residential Improvements | Q61: 105000 | R61: 42870 | W61: N | X61: N | Y61: 6110 KNOLL VALLEY DR # 204 | Z61: WILLOWBROOK | AA61: 0 | AB61: 1890.96 | AC61: 2028.6 | AD61: =FALSE() -> FALSE
A62: =TRUE() -> TRUE | B62: =FALSE() -> FALSE | C62: 2 | H62: =FALSE() -> FALSE | I62: =FALSE() -> FALSE | K62: DESHPANDE RAJ & SARADA | L62: 09-27-208-059 | M62: 0927208059 | N62: 6070 | O62: 26629 | P62: 40 - Residential Improvements | Q62: 58000 | R62: 42156 | W62: N | X62: N | Y62: 7425 BROOKDALE DR # 214 | Z62: DARIEN | AA62: 0 | AB62: 2106.82 | AC62: 2259.03 | AD62: =FALSE() -> FALSE
A63: =TRUE() -> TRUE | B63: =FALSE() -> FALSE | C63: 2 | G63: 2 | H63: =TRUE() -> TRUE | I63: =FALSE() -> FALSE | K63: MILLER LAURA D | L63: 09-27-414-010 | M63: 0927414010 | N63: 12292 | O63: 51203 | P63: 40 - Residential Improvements | R63: 43536 | W63: N | X63: N | Y63: 7544 CLARENDON HILLS # 10 | Z63: WILLOWBROOK | AA63: 0 | AB63: 2655.72 | AC63: 2844.98 | AD63: =FALSE() -> FALSE
A64: =TRUE() -> TRUE | B64: =FALSE() -> FALSE | C64: 2 | H64: =TRUE() -> TRUE | I64: =FALSE() -> FALSE | K64: FLISK ELENA | L64: 09-32-209-007 | M64: 0932209007 | N64: 7854 | O64: 47221 | P64: 40 - Residential Improvements | Q64: 156000 | R64: 39386 | W64: N | X64: N | Y64: 7930 WOODGLEN LN # 104 | Z64: DOWNERS GROVE | AA64: 0 | AB64: 2651.22 | AC64: 2840.17 | AD64: =FALSE() -> FALSE
A65: =TRUE() -> TRUE | B65: =FALSE() -> FALSE | C65: 2 | G65: 2 | H65: =TRUE() -> TRUE | I65: =FALSE() -> FALSE | K65: CARDY EVAN | L65: 09-35-114-049 | M65: 0935114049 | N65: 10704 | O65: 32786 | P65: 40 - Residential Improvements | Q65: 56000 | R65: 41071 | W65: Y | X65: N | Y65: 16W471 79TH ST # 4-101 | Z65: WILLOWBROOK | AA65: 0 | AB65: 1714.14 | AC65: 1839.85 | AD65: =FALSE() -> FALSE
A66: =TRUE() -> TRUE | B66: =FALSE() -> FALSE | C66: 3 | G66: 3 | H66: =FALSE() -> FALSE | I66: =FALSE() -> FALSE | K66: RICHAK DAVID | L66: 09-35-114-132 | M66: 0935114132 | N66: 7462 | O66: 24323 | P66: 40 - Residential Improvements | R66: 34159 | S66: 38600 | T66: 37876 | U66: 10000 | V66: 36531 | W66: Y | X66: N | Y66: 16W540 LAKE DR # 9-104 | Z66: WILLOWBROOK | AA66: 0 | AB66: 1148.8 | AC66: 1236.35 | AD66: =FALSE() -> FALSE
A67: =TRUE() -> TRUE | B67: =FALSE() -> FALSE | C67: 2 | H67: =FALSE() -> FALSE | I67: =FALSE() -> FALSE | K67: DIMITROV NICOLA | L67: 09-35-114-145 | M67: 0935114145 | N67: 10704 | O67: 32786 | P67: 40 - Residential Improvements | Q67: 86500 | R67: 42496 | W67: Y | X67: Y | Y67: 9S025 LAKE DR # 101 | Z67: WILLOWBROOK | AA67: 0 | AB67: 2100.52 | AC67: 2252.3 | AD67: =FALSE() -> FALSE
A68: =TRUE() -> TRUE | B68: =FALSE() -> FALSE | C68: 2 | G68: 2 | H68: =FALSE() -> FALSE | I68: =FALSE() -> FALSE | K68: PATEL TRUSHAR | L68: 09-35-114-213 | M68: 0935114213 | N68: 10704 | O68: 32786 | P68: 40 - Residential Improvements | Q68: 110000 | R68: 43698 | W68: Y | X68: N | Y68: 9S110 LAKE DR # 14-106 | Z68: WILLOWBROOK | AA68: 0 | AB68: 2100.52 | AC68: 2252.3 | AD68: =FALSE() -> FALSE
A69: =TRUE() -> TRUE | B69: =FALSE() -> FALSE | C69: 2 | H69: =FALSE() -> FALSE | I69: =FALSE() -> FALSE | K69: TRAVIS KIMBERLY | L69: 09-35-114-399 | M69: 0935114399 | N69: 10824 | O69: 32786 | P69: 40 - Residential Improvements | Q69: 160000 | R69: 45183 | W69: Y | X69: Y | Y69: 16W525 LAKE DR # 23-207 | Z69: WILLOWBROOK | AA69: 0 | AB69: 1719.92 | AC69: 1846.02 | AD69: =FALSE() -> FALSE
A70: =TRUE() -> TRUE | B70: =FALSE() -> FALSE | C70: 2 | H70: =FALSE() -> FALSE | I70: =FALSE() -> FALSE | K70: DAMBRAUSKAITE IRMA | L70: 09-35-114-451 | M70: 0935114451 | N70: 7473 | O70: 24323 | P70: 40 - Residential Improvements | Q70: 69500 | R70: 37386 | W70: Y | X70: N | Y70: 9S110 N FRONTAGE RD # 203 | Z70: WILLOWBROOK | AA70: 0 | AB70: 1149.32 | AC70: 1236.9 | AD70: =FALSE() -> FALSE
A71: =TRUE() -> TRUE | B71: =FALSE() -> FALSE | C71: 2 | H71: =FALSE() -> FALSE | I71: =FALSE() -> FALSE | K71: DIMITROV NICOLA | L71: 09-35-114-456 | M71: 0935114456 | N71: 10824 | O71: 32786 | P71: 40 - Residential Improvements | R71: 41239 | W71: Y | X71: N | Y71: 9S110 FRONTAGE RD # 26-208 | Z71: WILLOWBROOK | AA71: 0 | AB71: 1719.92 | AC71: 1846.02 | AD71: =FALSE() -> FALSE
A72: =TRUE() -> TRUE | B72: =FALSE() -> FALSE | C72: 3 | H72: =FALSE() -> FALSE | I72: =FALSE() -> FALSE | K72: BOYES MARIANNE | L72: 10-02-307-070 | M72: 1002307070 | N72: 7810 | O72: 23921 | P72: 40 - Residential Improvements | S72: 25000 | T72: 38758 | W72: N | X72: Y | Y72: 24 KINGERY QUARTER # 106 | Z72: WILLOWBROOK | AA72: 0 | AB72: 895.64 | AC72: 966.09 | AD72: =FALSE() -> FALSE
A73: =TRUE() -> TRUE | B73: =FALSE() -> FALSE | C73: 2 | H73: =FALSE() -> FALSE | I73: =FALSE() -> FALSE | K73: FLORES JOSHUA A | L73: 10-02-307-217 | M73: 1002307217 | N73: 10019 | O73: 32199 | P73: 40 - Residential Improvements | R73: 43531 | W73: N | X73: Y | Y73: 15A KINGERY QUARTER # 201 | Z73: WILLOWBROOK | AA73: 0 | AB73: 1948.18 | AC73: 2089.68 | AD73: =FALSE() -> FALSE
A74: =TRUE() -> TRUE | B74: =FALSE() -> FALSE | C74: 2 | H74: =FALSE() -> FALSE | I74: =FALSE() -> FALSE | K74: DIMITROV NICOLA | L74: 10-02-312-111 | M74: 1002312111 | N74: 8615 | O74: 37910 | P74: 40 - Residential Improvements | R74: 42356 | W74: N | X74: Y | Y74: 16W571 MOCKINGBIRD LN # 207 | Z74: WILLOWBROOK | AA74: 0 | AB74: 2648.86 | AC74: 2837.66 | AD74: =FALSE() -> FALSE
AB76: Total | AC76: =SUM(AC2:AC74) -> 156875.76
